{
 "company": "iceye",
 "source": "ashby",
 "board": "iceye",
 "fetched_at": "2026-07-14T17:46:01+00:00",
 "job_count": 139,
 "jobs": [
  {
   "job_id": "055bf193-bb2c-4af9-8cd8-96e421ae2940",
   "lineage_key": "satellite-launch-specialist@warsaw",
   "title": "Satellite Launch Specialist",
   "department": "Global Manufacturing Organization",
   "team": "Global Manufacturing Organization",
   "location": "Warsaw",
   "secondary_locations": [],
   "employment_type": "FullTime",
   "workplace_type": "Hybrid",
   "is_remote": true,
   "published_at": "2026-07-13T09:04:06.453+00:00",
   "url": "https://jobs.ashbyhq.com/iceye/055bf193-bb2c-4af9-8cd8-96e421ae2940",
   "description_sha256": "6c17d25f990193d9db1e7f88946373dff91c62ab8093e2e14be80b7212db3a94"
  },
  {
   "job_id": "06f113d6-1702-4346-9369-97d70d68738b",
   "lineage_key": "supplier-quality-engineer-mechanical@espoo",
   "title": "Supplier Quality Engineer (Mechanical)",
   "department": "Global Manufacturing Organization",
   "team": "Global Manufacturing Organization",
   "location": "Espoo",
   "secondary_locations": [],
   "employment_type": "FullTime",
   "workplace_type": "Hybrid",
   "is_remote": true,
   "published_at": "2026-06-25T09:37:15.157+00:00",
   "url": "https://jobs.ashbyhq.com/iceye/06f113d6-1702-4346-9369-97d70d68738b",
   "description_sha256": "bf6d8c68a3d489dd01cec87e105a57d517fc94108e7dd2a485c0c6385972ed12"
  },
  {
   "job_id": "07aafef7-94ec-4a8a-bbf8-bc5d8cca846a",
   "lineage_key": "senior-it-engineer-linux-client-platform@espoo",
   "title": "Senior IT Engineer (Linux Client Platform)",
   "department": "Operations",
   "team": "Operations",
   "location": "Espoo",
   "secondary_locations": [
    "Warsaw"
   ],
   "employment_type": "FullTime",
   "workplace_type": "Hybrid",
   "is_remote": true,
   "published_at": "2026-05-20T04:50:17.772+00:00",
   "url": "https://jobs.ashbyhq.com/iceye/07aafef7-94ec-4a8a-bbf8-bc5d8cca846a",
   "description_sha256": "a2f077a46b8ba51d70945a55ad3dc5b6dd5d4e81cbbf842fe57ccc25dd426010"
  },
  {
   "job_id": "09d02ba3-5ba6-4a11-bb30-74e42c22c485",
   "lineage_key": "satellite-production-senior-technician-electronics@valencia",
   "title": "Satellite Production Senior Technician, Electronics",
   "department": "Global Manufacturing Organization",
   "team": "Global Manufacturing Organization",
   "location": "Valencia",
   "secondary_locations": [],
   "employment_type": "FullTime",
   "workplace_type": "OnSite",
   "is_remote": false,
   "published_at": "2026-07-13T12:21:38.285+00:00",
   "url": "https://jobs.ashbyhq.com/iceye/09d02ba3-5ba6-4a11-bb30-74e42c22c485",
   "description_sha256": "91a751583b69f99c2ad60e435585bc7299557f8116c6dd536238c4e86f6f0776"
  },
  {
   "job_id": "0b21baf2-aca9-49d5-8a8e-d49803845f14",
   "lineage_key": "staff-electronics-engineer-avionics@espoo",
   "title": "Staff Electronics Engineer - Avionics",
   "department": "Engineering",
   "team": "Avionics",
   "location": "Espoo",
   "secondary_locations": [],
   "employment_type": "FullTime",
   "workplace_type": "Hybrid",
   "is_remote": true,
   "published_at": "2026-04-08T07:28:31.736+00:00",
   "url": "https://jobs.ashbyhq.com/iceye/0b21baf2-aca9-49d5-8a8e-d49803845f14",
   "description_sha256": "de5b0638f458b486c02a64ffb0555fc6edefe18d2cad73f2fcdfafa301d265e3"
  },
  {
   "job_id": "0d85e5cc-a568-41e5-817b-a872d6e8dbdc",
   "lineage_key": "uk-geospatial-intelligence-advisor@uk",
   "title": "UK Geospatial Intelligence Advisor",
   "department": "Missions",
   "team": "Missions Sales",
   "location": "UK",
   "secondary_locations": [],
   "employment_type": "FullTime",
   "workplace_type": "Hybrid",
   "is_remote": true,
   "published_at": "2026-06-19T07:35:20.768+00:00",
   "url": "https://jobs.ashbyhq.com/iceye/0d85e5cc-a568-41e5-817b-a872d6e8dbdc",
   "description_sha256": "872a8904d0af51ee28ba64f103aa5170eadb2e9a3caa3f100fc5e381bfd2f777"
  },
  {
   "job_id": "0ea7048b-1c32-4dab-9dac-099409e74112",
   "lineage_key": "senior-fpga-engineer@warsaw",
   "title": "Senior FPGA Engineer",
   "department": "Engineering",
   "team": "Flight Software",
   "location": "Warsaw",
   "secondary_locations": [],
   "employment_type": "FullTime",
   "workplace_type": "Hybrid",
   "is_remote": true,
   "published_at": "2026-05-11T11:47:49.296+00:00",
   "url": "https://jobs.ashbyhq.com/iceye/0ea7048b-1c32-4dab-9dac-099409e74112",
   "description_sha256": "5272c97928eb90fa441079c6d897d652d5e4ce92c4f65c9458edfb601f73fbdf"
  },
  {
   "job_id": "1197834e-3203-4546-8f55-2bde6fe39546",
   "lineage_key": "c-engineer-satellite-real-time-control-systems@espoo",
   "title": "C++ Engineer - Satellite Real-Time Control Systems",
   "department": "Engineering",
   "team": "Attitude and Orbit Control System Software",
   "location": "Espoo",
   "secondary_locations": [],
   "employment_type": "FullTime",
   "workplace_type": "Hybrid",
   "is_remote": true,
   "published_at": "2026-05-22T12:10:55.236+00:00",
   "url": "https://jobs.ashbyhq.com/iceye/1197834e-3203-4546-8f55-2bde6fe39546",
   "description_sha256": "6d29c53da7c3ffab568ad07a5d11bf7fa9aee638221f104e0f7d4c984bd89347"
  },
  {
   "job_id": "12ed4968-bb78-4bba-81c8-843536d39a78",
   "lineage_key": "flight-software-application-layer-intern@espoo",
   "title": "Flight Software Application Layer Intern",
   "department": "Engineering",
   "team": "Flight Software",
   "location": "Espoo",
   "secondary_locations": [],
   "employment_type": "FullTime",
   "workplace_type": "Hybrid",
   "is_remote": true,
   "published_at": "2026-06-02T13:25:46.508+00:00",
   "url": "https://jobs.ashbyhq.com/iceye/12ed4968-bb78-4bba-81c8-843536d39a78",
   "description_sha256": "c38078c786f1cf602cdcaabf41771418397cbe964dda41a602bc4f04aea49ea3"
  },
  {
   "job_id": "15ec7f83-01ba-46fc-91c6-88cd28bb6338",
   "lineage_key": "field-technician-uav-flight-operations@valencia",
   "title": "Field Technician (UAV Flight Operations)",
   "department": "Engineering",
   "team": "HAPS Avionics and Operations",
   "location": "Valencia",
   "secondary_locations": [],
   "employment_type": "FullTime",
   "workplace_type": "OnSite",
   "is_remote": false,
   "published_at": "2026-05-19T16:05:31.899+00:00",
   "url": "https://jobs.ashbyhq.com/iceye/15ec7f83-01ba-46fc-91c6-88cd28bb6338",
   "description_sha256": "2789c15d148e09fe224e78565c7740bfe3202567bdd04f8445e8b068b6c2ef05"
  },
  {
   "job_id": "1628a483-ff24-4978-b710-abd49f32bce5",
   "lineage_key": "program-manager-uae@united-arab-emirates",
   "title": "Program Manager - UAE",
   "department": "Missions",
   "team": "Missions Programs",
   "location": "United Arab Emirates",
   "secondary_locations": [],
   "employment_type": "FullTime",
   "workplace_type": "Hybrid",
   "is_remote": true,
   "published_at": "2026-06-05T13:00:42.705+00:00",
   "url": "https://jobs.ashbyhq.com/iceye/1628a483-ff24-4978-b710-abd49f32bce5",
   "description_sha256": "443f8280c1b1555d48b54858c570cc03aa30845782f069f1fc3874e346f9510d"
  },
  {
   "job_id": "18952119-94cf-46c8-a6b8-9c05df99dd34",
   "lineage_key": "satellite-production-technician-integration-mechanical-thermal@valencia",
   "title": "Satellite Production Technician, Integration, Mechanical & Thermal",
   "department": "Global Manufacturing Organization",
   "team": "Global Manufacturing Organization",
   "location": "Valencia",
   "secondary_locations": [],
   "employment_type": "FullTime",
   "workplace_type": "OnSite",
   "is_remote": false,
   "published_at": "2026-07-13T09:30:11.898+00:00",
   "url": "https://jobs.ashbyhq.com/iceye/18952119-94cf-46c8-a6b8-9c05df99dd34",
   "description_sha256": "e38a6d668698ee3cac8a903452fdd3eb98e32546a44a3c06086c645b675bd23e"
  },
  {
   "job_id": "1ac23b1c-f069-48c3-978f-1b37fdf0787f",
   "lineage_key": "forward-deployed-geospatial-engineer-sar-intelligence-greece@athens",
   "title": "Forward Deployed Geospatial Engineer - SAR Intelligence, Greece",
   "department": "Forward Deployed Engineering",
   "team": "Forward Deployed Engineering",
   "location": "Athens",
   "secondary_locations": [
    "Greece"
   ],
   "employment_type": "FullTime",
   "workplace_type": "OnSite",
   "is_remote": false,
   "published_at": "2026-07-01T08:25:06.569+00:00",
   "url": "https://jobs.ashbyhq.com/iceye/1ac23b1c-f069-48c3-978f-1b37fdf0787f",
   "description_sha256": "56ffa19daf621b7032e204379eac691b2ae0bb3d36a010705051468868e22056"
  },
  {
   "job_id": "1db756b7-7d44-4232-aaae-4632e727850f",
   "lineage_key": "staff-product-designer@espoo",
   "title": "Staff Product Designer",
   "department": "Missions",
   "team": "Product Management",
   "location": "Espoo",
   "secondary_locations": [],
   "employment_type": "FullTime",
   "workplace_type": "Hybrid",
   "is_remote": true,
   "published_at": "2026-04-15T11:44:49.661+00:00",
   "url": "https://jobs.ashbyhq.com/iceye/1db756b7-7d44-4232-aaae-4632e727850f",
   "description_sha256": "ef6f658d70683a78f62a33361439cc8e9990f991fcc840b04e4b522ab22f5495"
  },
  {
   "job_id": "1ffce4d4-4088-4336-9007-622dc10399fb",
   "lineage_key": "senior-software-engineer-developer-enablement@espoo",
   "title": "Senior Software Engineer (Developer Enablement)",
   "department": "Engineering",
   "team": "Developer Enablement",
   "location": "Espoo",
   "secondary_locations": [],
   "employment_type": "FullTime",
   "workplace_type": "Hybrid",
   "is_remote": true,
   "published_at": "2026-06-02T08:05:25.484+00:00",
   "url": "https://jobs.ashbyhq.com/iceye/1ffce4d4-4088-4336-9007-622dc10399fb",
   "description_sha256": "b74dd552c06225649ab21d3f2a60c73ed0b692fd663f2982c7850c5e3948ee24"
  },
  {
   "job_id": "2048d1e8-7667-466a-a72a-d754cbcb42f2",
   "lineage_key": "senior-c-engineer-satellite-real-time-control-systems@espoo",
   "title": "Senior C++ Engineer - Satellite Real-Time Control Systems",
   "department": "Engineering",
   "team": "Attitude and Orbit Control System",
   "location": "Espoo",
   "secondary_locations": [],
   "employment_type": "FullTime",
   "workplace_type": "Hybrid",
   "is_remote": true,
   "published_at": "2026-04-13T16:12:46.683+00:00",
   "url": "https://jobs.ashbyhq.com/iceye/2048d1e8-7667-466a-a72a-d754cbcb42f2",
   "description_sha256": "63744517323f55c3d9a5c951fd880215b0a69008856c53d5312480a3c4919738"
  },
  {
   "job_id": "21ab33e4-31f0-4324-8fd0-96de29e808b1",
   "lineage_key": "staff-software-engineer-fleet-control-and-satellite-communications@espoo",
   "title": "Staff Software Engineer (Fleet Control and Satellite Communications)",
   "department": "Engineering",
   "team": "Fleet Control and Communications",
   "location": "Espoo",
   "secondary_locations": [],
   "employment_type": "FullTime",
   "workplace_type": "Hybrid",
   "is_remote": true,
   "published_at": "2026-04-23T07:35:17.458+00:00",
   "url": "https://jobs.ashbyhq.com/iceye/21ab33e4-31f0-4324-8fd0-96de29e808b1",
   "description_sha256": "a870956e3deaa2a4a0355260ee01c8f4b9046147f22222bc19264af8a0d0df12"
  },
  {
   "job_id": "245a08c3-81a1-4cee-8867-72bbf034f15d",
   "lineage_key": "head-of-global-manufacturing-capability-training@espoo",
   "title": "Head of Global Manufacturing Capability & Training",
   "department": "Global Manufacturing Organization",
   "team": "Global Manufacturing Infrastructure",
   "location": "Espoo",
   "secondary_locations": [],
   "employment_type": "FullTime",
   "workplace_type": "Hybrid",
   "is_remote": true,
   "published_at": "2026-05-15T10:04:06.565+00:00",
   "url": "https://jobs.ashbyhq.com/iceye/245a08c3-81a1-4cee-8867-72bbf034f15d",
   "description_sha256": "0046ca36ef3c6716bd6f58b13a156e52c77264221876011cf55b52f60cca76d2"
  },
  {
   "job_id": "25d1fe95-5578-4cc8-8b5a-334e238e6f3d",
   "lineage_key": "finance-manager@new-dehli",
   "title": "Finance Manager",
   "department": "Finance",
   "team": "Finance",
   "location": "New Dehli",
   "secondary_locations": [],
   "employment_type": "FullTime",
   "workplace_type": "",
   "is_remote": false,
   "published_at": "2026-07-02T16:08:24.106+00:00",
   "url": "https://jobs.ashbyhq.com/iceye/25d1fe95-5578-4cc8-8b5a-334e238e6f3d",
   "description_sha256": "9a67c4f963702931ff280b411fd29794859921184e9935c751b1ecc80c7d9cf9"
  },
  {
   "job_id": "26767edd-7f2f-4cb0-a8a4-9895a43f4848",
   "lineage_key": "head-of-operations@lisbon",
   "title": "Head of Operations",
   "department": "Operations",
   "team": "Operations",
   "location": "Lisbon",
   "secondary_locations": [],
   "employment_type": "FullTime",
   "workplace_type": "Hybrid",
   "is_remote": true,
   "published_at": "2026-07-09T12:41:31.256+00:00",
   "url": "https://jobs.ashbyhq.com/iceye/26767edd-7f2f-4cb0-a8a4-9895a43f4848",
   "description_sha256": "fba000a7af6b445964cfb4c912a2622d703337900999bbec3346b485bff7eb09"
  },
  {
   "job_id": "29585bb4-72f2-4199-929a-3b2e932cb66c",
   "lineage_key": "forward-deployed-ai-engineer-uae@berlin",
   "title": "Forward Deployed AI Engineer, UAE",
   "department": "Forward Deployed Engineering",
   "team": "Forward Deployed Engineering",
   "location": "Berlin",
   "secondary_locations": [],
   "employment_type": "FullTime",
   "workplace_type": "",
   "is_remote": false,
   "published_at": "2026-07-01T07:30:48.670+00:00",
   "url": "https://jobs.ashbyhq.com/iceye/29585bb4-72f2-4199-929a-3b2e932cb66c",
   "description_sha256": "f80a70a140051aa84035d2833987b58b227179490be3db661bceb406865e8434"
  },
  {
   "job_id": "2a0250ec-cd39-4589-9ee9-f1bffd4a4975",
   "lineage_key": "senior-mechanical-test-engineer@espoo",
   "title": "Senior Mechanical Test Engineer",
   "department": "Engineering",
   "team": "Mechanical Engineering",
   "location": "Espoo",
   "secondary_locations": [],
   "employment_type": "FullTime",
   "workplace_type": "Hybrid",
   "is_remote": true,
   "published_at": "2026-04-08T07:29:19.720+00:00",
   "url": "https://jobs.ashbyhq.com/iceye/2a0250ec-cd39-4589-9ee9-f1bffd4a4975",
   "description_sha256": "96a5581e5d1c1bee26ae95dcc4295ab2f199349076a8d27b782f0441170e328e"
  },
  {
   "job_id": "2a7fa616-d6b3-469d-a724-73150c417fac",
   "lineage_key": "staff-optical-engineer@warsaw",
   "title": "Staff Optical Engineer",
   "department": "Engineering",
   "team": "Optical System",
   "location": "Warsaw",
   "secondary_locations": [],
   "employment_type": "FullTime",
   "workplace_type": "Hybrid",
   "is_remote": true,
   "published_at": "2026-07-13T19:19:43.575+00:00",
   "url": "https://jobs.ashbyhq.com/iceye/2a7fa616-d6b3-469d-a724-73150c417fac",
   "description_sha256": "f628801b95f357e1b305482cec1dd56e2b6ce429e55492467f4578319e328a80"
  },
  {
   "job_id": "2add20af-74f0-43e9-b959-6470084b1091",
   "lineage_key": "sales-operations-specialist@espoo",
   "title": "Sales Operations Specialist",
   "department": "Finance",
   "team": "Finance",
   "location": "Espoo",
   "secondary_locations": [],
   "employment_type": "FullTime",
   "workplace_type": "Hybrid",
   "is_remote": true,
   "published_at": "2026-07-13T08:29:40.808+00:00",
   "url": "https://jobs.ashbyhq.com/iceye/2add20af-74f0-43e9-b959-6470084b1091",
   "description_sha256": "cc4b4080586813c8b009d550fa270343df304135abe61ec765b2e998dbebc41d"
  },
  {
   "job_id": "2ef68fcc-6ce8-476e-8c94-6e7b099842e9",
   "lineage_key": "forward-deployed-ai-engineer-portugal@lisbon",
   "title": "Forward Deployed AI Engineer, Portugal",
   "department": "Forward Deployed Engineering",
   "team": "Forward Deployed Engineering",
   "location": "Lisbon",
   "secondary_locations": [
    "Portugal"
   ],
   "employment_type": "FullTime",
   "workplace_type": "Hybrid",
   "is_remote": true,
   "published_at": "2026-06-26T08:52:57.811+00:00",
   "url": "https://jobs.ashbyhq.com/iceye/2ef68fcc-6ce8-476e-8c94-6e7b099842e9",
   "description_sha256": "79704c656c29d562ca79f3f2e785e189646f499bfcc3a48f03a1c7e02c3de5aa"
  },
  {
   "job_id": "30035258-9970-4f6f-a5ba-7b770c6b941d",
   "lineage_key": "global-manufacturing-infrastructure-engineer@espoo",
   "title": "Global Manufacturing  Infrastructure Engineer",
   "department": "Global Manufacturing Organization",
   "team": "Global Manufacturing Infrastructure",
   "location": "Espoo",
   "secondary_locations": [],
   "employment_type": "FullTime",
   "workplace_type": "Hybrid",
   "is_remote": true,
   "published_at": "2026-04-30T11:57:51.812+00:00",
   "url": "https://jobs.ashbyhq.com/iceye/30035258-9970-4f6f-a5ba-7b770c6b941d",
   "description_sha256": "e7841883b7fd2a74b25c9cf692913d005cf0d95ca114708e67d17a6fb954315d"
  },
  {
   "job_id": "307e5ecf-9033-424d-b6e5-39d0483e7f49",
   "lineage_key": "senior-electronics-engineer-radar-payload-team@espoo",
   "title": "Senior Electronics Engineer, Radar Payload Team",
   "department": "Engineering",
   "team": "Radar Payload",
   "location": "Espoo",
   "secondary_locations": [],
   "employment_type": "FullTime",
   "workplace_type": "Hybrid",
   "is_remote": true,
   "published_at": "2026-06-12T06:11:02.758+00:00",
   "url": "https://jobs.ashbyhq.com/iceye/307e5ecf-9033-424d-b6e5-39d0483e7f49",
   "description_sha256": "a5f13908e3f4cf066171a51c2d00bec3df6a6397a5a93a2149170b3ee3702a79"
  },
  {
   "job_id": "3177be0f-5997-45cf-bbdb-60b1c38543ea",
   "lineage_key": "thermal-harness-ait-engineer@valencia",
   "title": "Thermal & Harness AIT Engineer",
   "department": "Global Manufacturing Organization",
   "team": "Global Manufacturing Organization",
   "location": "Valencia",
   "secondary_locations": [],
   "employment_type": "FullTime",
   "workplace_type": "OnSite",
   "is_remote": false,
   "published_at": "2026-07-13T12:33:02.670+00:00",
   "url": "https://jobs.ashbyhq.com/iceye/3177be0f-5997-45cf-bbdb-60b1c38543ea",
   "description_sha256": "9cf07ac35d9ce93d322c7efb630a73c86703a976ceed04bf481f34efc58e929d"
  },
  {
   "job_id": "332b1d49-0d7e-43de-a460-41e36bd42519",
   "lineage_key": "software-ait-engineer@valencia",
   "title": "Software AIT Engineer",
   "department": "Global Manufacturing Organization",
   "team": "Global Manufacturing Organization",
   "location": "Valencia",
   "secondary_locations": [],
   "employment_type": "FullTime",
   "workplace_type": "OnSite",
   "is_remote": false,
   "published_at": "2026-07-13T09:39:39.273+00:00",
   "url": "https://jobs.ashbyhq.com/iceye/332b1d49-0d7e-43de-a460-41e36bd42519",
   "description_sha256": "1d7c427b13cac80ffd9296f846a9dfda11becd72da086950ce5201ef2cfa75af"
  },
  {
   "job_id": "34f68a39-6743-4af1-ae67-bd0ef78c904e",
   "lineage_key": "obc-comms-ait-engineer@espoo",
   "title": "OBC & Comms AIT engineer",
   "department": "Global Manufacturing Organization",
   "team": "FI AIT Engineering",
   "location": "Espoo",
   "secondary_locations": [],
   "employment_type": "FullTime",
   "workplace_type": "Hybrid",
   "is_remote": true,
   "published_at": "2026-05-25T19:10:18.945+00:00",
   "url": "https://jobs.ashbyhq.com/iceye/34f68a39-6743-4af1-ae67-bd0ef78c904e",
   "description_sha256": "9ba37bc106dda75861c0d2feaa987b4e7c76c9dcdee95f1ecec0ac0a241d023e"
  },
  {
   "job_id": "35528f9f-8244-465e-bf4b-799b8fffed53",
   "lineage_key": "configuration-manager@valencia",
   "title": "Configuration Manager",
   "department": "Global Manufacturing Organization",
   "team": "Global Manufacturing Organization",
   "location": "Valencia",
   "secondary_locations": [],
   "employment_type": "FullTime",
   "workplace_type": "OnSite",
   "is_remote": false,
   "published_at": "2026-07-03T12:39:48.411+00:00",
   "url": "https://jobs.ashbyhq.com/iceye/35528f9f-8244-465e-bf4b-799b8fffed53",
   "description_sha256": "4a8e71bd3f576ede667119c19721fac850af3860cd970987551af1d461e08c5f"
  },
  {
   "job_id": "37ce25c9-e16c-45d7-8891-f808c76e1102",
   "lineage_key": "senior-system-engineer-ground-systems-hardware@espoo",
   "title": "Senior System Engineer (Ground Systems Hardware)",
   "department": "Engineering",
   "team": "Platform & Release Engineering",
   "location": "Espoo",
   "secondary_locations": [],
   "employment_type": "FullTime",
   "workplace_type": "Hybrid",
   "is_remote": true,
   "published_at": "2026-04-20T08:30:26.834+00:00",
   "url": "https://jobs.ashbyhq.com/iceye/37ce25c9-e16c-45d7-8891-f808c76e1102",
   "description_sha256": "b76f890341520c9ad8a509f41d0204e77d1c997ed64faba841b9dbd46c6019d5"
  },
  {
   "job_id": "38a65e7e-1063-4071-8aba-0184ab09f996",
   "lineage_key": "missions-sales-director-indonesia@indonesia",
   "title": "Missions Sales Director, Indonesia",
   "department": "Missions",
   "team": "Missions Sales",
   "location": "Indonesia",
   "secondary_locations": [],
   "employment_type": "FullTime",
   "workplace_type": "Remote",
   "is_remote": true,
   "published_at": "2026-06-26T07:51:36.367+00:00",
   "url": "https://jobs.ashbyhq.com/iceye/38a65e7e-1063-4071-8aba-0184ab09f996",
   "description_sha256": "fafc3a6e62a2bb9859663f45728f621926f92c7f9c52a381d64216ddf4a975d4"
  },
  {
   "job_id": "3eb0f7b1-ab19-4d41-b633-dfeea0990086",
   "lineage_key": "configuration-specialist@espoo",
   "title": "Configuration Specialist",
   "department": "Global Manufacturing Organization",
   "team": "Global Manufacturing Organization",
   "location": "Espoo",
   "secondary_locations": [],
   "employment_type": "FullTime",
   "workplace_type": "Hybrid",
   "is_remote": true,
   "published_at": "2026-06-24T16:16:41.423+00:00",
   "url": "https://jobs.ashbyhq.com/iceye/3eb0f7b1-ab19-4d41-b633-dfeea0990086",
   "description_sha256": "1007bdcad479ebd212c936dcf6deab116009ff8858a5c1ff2288bbfae2e01cfd"
  },
  {
   "job_id": "431baaab-347b-485b-a52a-67d18dcbc2be",
   "lineage_key": "isr-operator-iceye-japan@tokyo",
   "title": "ISR Operator – ICEYE Japan",
   "department": "Missions",
   "team": "Local Subsidiaries",
   "location": "Tokyo",
   "secondary_locations": [],
   "employment_type": "FullTime",
   "workplace_type": "Hybrid",
   "is_remote": true,
   "published_at": "2026-05-22T03:40:27.081+00:00",
   "url": "https://jobs.ashbyhq.com/iceye/431baaab-347b-485b-a52a-67d18dcbc2be",
   "description_sha256": "0e56b0f18cfa43ed2edfd1a6553e4c2f6df3432e66a95cbe8a97f69759a91164"
  },
  {
   "job_id": "4411cffa-570c-4adf-a0df-5296d5cab351",
   "lineage_key": "software-engineer-orbit-determination-team@espoo",
   "title": "Software Engineer (Orbit Determination Team)",
   "department": "Engineering",
   "team": "Orbit Determination",
   "location": "Espoo",
   "secondary_locations": [],
   "employment_type": "FullTime",
   "workplace_type": "Hybrid",
   "is_remote": true,
   "published_at": "2026-04-09T08:44:14.315+00:00",
   "url": "https://jobs.ashbyhq.com/iceye/4411cffa-570c-4adf-a0df-5296d5cab351",
   "description_sha256": "b01973bf9318f8e2ed4c8e2b3e5cb398400aebad4c8ffc217dc372c00fad33ac"
  },
  {
   "job_id": "4470b416-a308-41a3-a967-293389b62beb",
   "lineage_key": "program-manager-germany@berlin",
   "title": "Program Manager - Germany",
   "department": "Missions",
   "team": "Missions Programs",
   "location": "Berlin",
   "secondary_locations": [
    "Munich"
   ],
   "employment_type": "FullTime",
   "workplace_type": "Hybrid",
   "is_remote": true,
   "published_at": "2026-06-25T12:27:28.896+00:00",
   "url": "https://jobs.ashbyhq.com/iceye/4470b416-a308-41a3-a967-293389b62beb",
   "description_sha256": "0fe4ca53d2c55b838c829ecb7640366f87b53a5d056e83b56842ca71e25a5a93"
  },
  {
   "job_id": "45422d7a-13ca-442e-97e8-ab5c056db6db",
   "lineage_key": "launch-operational-coordinator@espoo",
   "title": "Launch Operational Coordinator",
   "department": "Global Manufacturing Organization",
   "team": "Global Manufacturing Organization",
   "location": "Espoo",
   "secondary_locations": [],
   "employment_type": "FullTime",
   "workplace_type": "Hybrid",
   "is_remote": true,
   "published_at": "2026-07-13T08:51:34.638+00:00",
   "url": "https://jobs.ashbyhq.com/iceye/45422d7a-13ca-442e-97e8-ab5c056db6db",
   "description_sha256": "699dbdeea27ba4c533422c0f6ad272dddeba6626ec93d06464c2907854b464de"
  },
  {
   "job_id": "4572f413-69db-4c73-a8a4-920a26107dbe",
   "lineage_key": "sar-launch-specialist@espoo",
   "title": "SAR Launch Specialist",
   "department": "Global Manufacturing Organization",
   "team": "Global Manufacturing Organization",
   "location": "Espoo",
   "secondary_locations": [],
   "employment_type": "FullTime",
   "workplace_type": "OnSite",
   "is_remote": false,
   "published_at": "2026-07-13T08:42:41.972+00:00",
   "url": "https://jobs.ashbyhq.com/iceye/4572f413-69db-4c73-a8a4-920a26107dbe",
   "description_sha256": "71306f7ec58ea7ee30da6562233afc13644bb15f045cd92c00f51cf6cce95552"
  },
  {
   "job_id": "482053f5-a2b0-4be8-b513-ec9524346fd6",
   "lineage_key": "it-site-engineer-germany@berlin",
   "title": "IT Site Engineer - Germany",
   "department": "Operations",
   "team": "IT",
   "location": "Berlin",
   "secondary_locations": [],
   "employment_type": "FullTime",
   "workplace_type": "",
   "is_remote": false,
   "published_at": "2026-07-13T07:16:41.993+00:00",
   "url": "https://jobs.ashbyhq.com/iceye/482053f5-a2b0-4be8-b513-ec9524346fd6",
   "description_sha256": "d31034e4a8e976664dff93331b9c4651b04d53e0f6287d8c1e8b9d8a277af1fa"
  },
  {
   "job_id": "50ea94b9-1799-49ed-98f2-fdf29bf4fef8",
   "lineage_key": "facility-management-team-lead@espoo",
   "title": "Facility Management Team Lead",
   "department": "Global Manufacturing Organization",
   "team": "Global Manufacturing Organization",
   "location": "Espoo",
   "secondary_locations": [],
   "employment_type": "FullTime",
   "workplace_type": "Hybrid",
   "is_remote": true,
   "published_at": "2026-07-10T08:44:13.214+00:00",
   "url": "https://jobs.ashbyhq.com/iceye/50ea94b9-1799-49ed-98f2-fdf29bf4fef8",
   "description_sha256": "bfbf14de06e5dc8074d8134aeeed6c5a15f4e7790bd40d89cda98dce1737dd5d"
  },
  {
   "job_id": "54476294-191e-4e00-96a2-922d3ac4ca16",
   "lineage_key": "quality-control-technician-mechanical@athens",
   "title": "Quality Control Technician - Mechanical",
   "department": "Global Manufacturing Organization",
   "team": "Production Greece",
   "location": "Athens",
   "secondary_locations": [],
   "employment_type": "FullTime",
   "workplace_type": "OnSite",
   "is_remote": false,
   "published_at": "2026-06-04T15:08:53.763+00:00",
   "url": "https://jobs.ashbyhq.com/iceye/54476294-191e-4e00-96a2-922d3ac4ca16",
   "description_sha256": "48a3d9210accffd086725c4166329a85322dd2eb1f54df383cbfb084b57a05a0"
  },
  {
   "job_id": "54504736-2e30-4a8c-a8a6-264e59712dc8",
   "lineage_key": "ait-technician@espoo",
   "title": "AIT Technician",
   "department": "Engineering",
   "team": "Testing Engineering",
   "location": "Espoo",
   "secondary_locations": [],
   "employment_type": "FullTime",
   "workplace_type": "Hybrid",
   "is_remote": true,
   "published_at": "2026-05-18T15:32:59.380+00:00",
   "url": "https://jobs.ashbyhq.com/iceye/54504736-2e30-4a8c-a8a6-264e59712dc8",
   "description_sha256": "79b4c67a5306e0b5a5930920a8881c4b7f8d4fd77a506fa9e516bfe104d631cd"
  },
  {
   "job_id": "545051b5-35a4-4859-a33a-095037a0988e",
   "lineage_key": "senior-fp-a-manager@espoo",
   "title": "Senior FP&A Manager",
   "department": "Finance",
   "team": "Finance Business Partnering",
   "location": "Espoo",
   "secondary_locations": [],
   "employment_type": "FullTime",
   "workplace_type": "Hybrid",
   "is_remote": true,
   "published_at": "2026-06-18T11:35:49.302+00:00",
   "url": "https://jobs.ashbyhq.com/iceye/545051b5-35a4-4859-a33a-095037a0988e",
   "description_sha256": "d47f15c0d0946d9376b4242d4eb43ab653b07c3b6c37c903bb61c16265b820a7"
  },
  {
   "job_id": "5666cc2e-53f7-4e19-b971-b183adb5555c",
   "lineage_key": "staff-developer-advocate@espoo",
   "title": "Staff Developer Advocate",
   "department": "Product Management",
   "team": "Product Management",
   "location": "Espoo",
   "secondary_locations": [],
   "employment_type": "FullTime",
   "workplace_type": "Hybrid",
   "is_remote": true,
   "published_at": "2026-07-05T18:02:59.695+00:00",
   "url": "https://jobs.ashbyhq.com/iceye/5666cc2e-53f7-4e19-b971-b183adb5555c",
   "description_sha256": "b820b5ed7bb2637d0735157c6b5cfd4f7bcdab5b1356902d7592d6696034c6d1"
  },
  {
   "job_id": "5bc4767f-7ae6-429a-a784-a9d260680462",
   "lineage_key": "smart-manufacturing-engineer-sw-electronics@espoo",
   "title": "Smart Manufacturing Engineer, SW & Electronics",
   "department": "Global Manufacturing Organization",
   "team": "Digital Transformation & Smart Manufacturing",
   "location": "Espoo",
   "secondary_locations": [],
   "employment_type": "FullTime",
   "workplace_type": "Hybrid",
   "is_remote": true,
   "published_at": "2026-04-28T13:13:51.694+00:00",
   "url": "https://jobs.ashbyhq.com/iceye/5bc4767f-7ae6-429a-a784-a9d260680462",
   "description_sha256": "8b450eabf15592bc2f0539e75a7f6feaf0e57cad5706a61eae53c33eca3b6905"
  },
  {
   "job_id": "5d1c9124-8b45-4b12-b3b4-8e91168afbbc",
   "lineage_key": "senior-optomechanical-engineer@warsaw",
   "title": "Senior Optomechanical Engineer",
   "department": "Engineering",
   "team": "Optical System",
   "location": "Warsaw",
   "secondary_locations": [],
   "employment_type": "FullTime",
   "workplace_type": "Hybrid",
   "is_remote": true,
   "published_at": "2026-07-13T19:14:52.436+00:00",
   "url": "https://jobs.ashbyhq.com/iceye/5d1c9124-8b45-4b12-b3b4-8e91168afbbc",
   "description_sha256": "3af4692fe5beb5e77889a666bd1d2ee031c11b98b159c0cd7582d5016615fbfc"
  },
  {
   "job_id": "5d8393c0-ab67-4a3b-b39f-3a183a4665fb",
   "lineage_key": "cleanroom-lab-manager-athens@greece",
   "title": "Cleanroom & Lab Manager - Athens",
   "department": "Global Manufacturing Organization",
   "team": "Production Greece",
   "location": "Greece",
   "secondary_locations": [],
   "employment_type": "FullTime",
   "workplace_type": "OnSite",
   "is_remote": false,
   "published_at": "2026-04-27T13:16:32.945+00:00",
   "url": "https://jobs.ashbyhq.com/iceye/5d8393c0-ab67-4a3b-b39f-3a183a4665fb",
   "description_sha256": "decdd73e527b02e09f876c0ac65b4bc40ededdc2009f25a8e699eed4a7151276"
  },
  {
   "job_id": "5fac41b2-14eb-419b-8bf7-d10e5603c2fa",
   "lineage_key": "flood-data-scientist@espoo",
   "title": "Flood Data Scientist",
   "department": "Solutions",
   "team": "Product Engineering",
   "location": "Espoo",
   "secondary_locations": [],
   "employment_type": "FullTime",
   "workplace_type": "Hybrid",
   "is_remote": true,
   "published_at": "2026-04-15T04:31:54.088+00:00",
   "url": "https://jobs.ashbyhq.com/iceye/5fac41b2-14eb-419b-8bf7-d10e5603c2fa",
   "description_sha256": "31ec0e56d195836ce2b716348053dc3b8cddb1f9bb501b99db4819818e8303f8"
  },
  {
   "job_id": "63ba947b-f760-4432-99cb-0c4428eca916",
   "lineage_key": "small-opportunities-seller-business-development-specialist@espoo",
   "title": "Small Opportunities Seller / Business Development Specialist",
   "department": "Data",
   "team": "Data",
   "location": "Espoo",
   "secondary_locations": [
    "Amsterdam",
    "Valencia",
    "Berlin",
    "Athens",
    "Warsaw"
   ],
   "employment_type": "FullTime",
   "workplace_type": "Hybrid",
   "is_remote": true,
   "published_at": "2026-06-25T15:06:30.598+00:00",
   "url": "https://jobs.ashbyhq.com/iceye/63ba947b-f760-4432-99cb-0c4428eca916",
   "description_sha256": "3bdf68d4c9086c4373ebb842bf4e76c632dce4bd9c0faafb771e8c7fd26de46b"
  },
  {
   "job_id": "6796ce6b-05bf-41ec-a53c-bc882ac74d3c",
   "lineage_key": "forward-deployed-geospatial-engineer-sar-intelligence-berlin@berlin",
   "title": "Forward Deployed Geospatial Engineer - SAR Intelligence, Berlin",
   "department": "Forward Deployed Engineering",
   "team": "Forward Deployed Engineering",
   "location": "Berlin",
   "secondary_locations": [],
   "employment_type": "FullTime",
   "workplace_type": "",
   "is_remote": false,
   "published_at": "2026-07-01T07:38:53.046+00:00",
   "url": "https://jobs.ashbyhq.com/iceye/6796ce6b-05bf-41ec-a53c-bc882ac74d3c",
   "description_sha256": "1cc4a18a4054da91acfa5539bbf807d6e67759f1dd40d9af02819e1afd3e9ffe"
  },
  {
   "job_id": "680034d6-e73c-47d8-8916-4a4d3f5f1c91",
   "lineage_key": "intelligence-analyst@berlin",
   "title": "Intelligence Analyst",
   "department": "CEO Office",
   "team": "CEO Office",
   "location": "Berlin",
   "secondary_locations": [],
   "employment_type": "FullTime",
   "workplace_type": "OnSite",
   "is_remote": false,
   "published_at": "2026-06-18T09:48:38.960+00:00",
   "url": "https://jobs.ashbyhq.com/iceye/680034d6-e73c-47d8-8916-4a4d3f5f1c91",
   "description_sha256": "3c64b8ce7c2942523e56df3f1d599e39030f287d8f5cceca38d8ae221facbc6a"
  },
  {
   "job_id": "688e6eed-057d-444e-afc2-de87f2d9ba2c",
   "lineage_key": "stock-manager-athens@greece",
   "title": "Stock Manager - Athens",
   "department": "Global Manufacturing Organization",
   "team": "GR Stock Management",
   "location": "Greece",
   "secondary_locations": [],
   "employment_type": "FullTime",
   "workplace_type": "OnSite",
   "is_remote": false,
   "published_at": "2026-04-12T20:59:28.760+00:00",
   "url": "https://jobs.ashbyhq.com/iceye/688e6eed-057d-444e-afc2-de87f2d9ba2c",
   "description_sha256": "816bcde00778067c088c62b705ef0f9dd4bf9da908d70d0cd5a92afe1afa9981"
  },
  {
   "job_id": "6c374442-a611-40d4-8ba7-4366bd623885",
   "lineage_key": "senior-netsuite-functional-consultant@espoo",
   "title": "Senior NetSuite Functional Consultant",
   "department": "Operations",
   "team": "Applications & Integrations",
   "location": "Espoo",
   "secondary_locations": [],
   "employment_type": "FullTime",
   "workplace_type": "Hybrid",
   "is_remote": true,
   "published_at": "2026-06-18T14:52:15.804+00:00",
   "url": "https://jobs.ashbyhq.com/iceye/6c374442-a611-40d4-8ba7-4366bd623885",
   "description_sha256": "9821eb2f148265216accb68f29b6f7012f4900f2d5e621bdbd8247d59f4c0253"
  },
  {
   "job_id": "6e531bd0-02f1-4191-91dd-f16910246d23",
   "lineage_key": "senior-rf-engineer-radar-payload-team@espoo",
   "title": "Senior RF Engineer, Radar Payload Team",
   "department": "Engineering",
   "team": "Radar Payload",
   "location": "Espoo",
   "secondary_locations": [],
   "employment_type": "FullTime",
   "workplace_type": "Hybrid",
   "is_remote": true,
   "published_at": "2026-04-08T07:31:37.367+00:00",
   "url": "https://jobs.ashbyhq.com/iceye/6e531bd0-02f1-4191-91dd-f16910246d23",
   "description_sha256": "c83c32e24165aaf9150a34be29d4b1003e385890c73b5e71e99ffd7012b2804a"
  },
  {
   "job_id": "6f4faf66-f7c0-4e89-a10f-6e9589646e0c",
   "lineage_key": "structural-analysis-engineer-team-lead@espoo",
   "title": "Structural Analysis Engineer, Team Lead",
   "department": "Engineering",
   "team": "Mechanical Engineering",
   "location": "Espoo",
   "secondary_locations": [],
   "employment_type": "FullTime",
   "workplace_type": "Hybrid",
   "is_remote": true,
   "published_at": "2026-04-14T13:05:15.294+00:00",
   "url": "https://jobs.ashbyhq.com/iceye/6f4faf66-f7c0-4e89-a10f-6e9589646e0c",
   "description_sha256": "f5ee52738846db421f1637679ebd29b3cb7f9ccb34f14f59c0ec5f8577f83bc9"
  },
  {
   "job_id": "7072cbcc-12a0-4ee5-a9ff-cbd6dd3d4764",
   "lineage_key": "isr-cell-operator-germany@berlin",
   "title": "ISR Cell Operator - Germany",
   "department": "CEO Office",
   "team": "CEO Office",
   "location": "Berlin",
   "secondary_locations": [],
   "employment_type": "FullTime",
   "workplace_type": "",
   "is_remote": false,
   "published_at": "2026-06-18T06:27:04.087+00:00",
   "url": "https://jobs.ashbyhq.com/iceye/7072cbcc-12a0-4ee5-a9ff-cbd6dd3d4764",
   "description_sha256": "174dd99b90633842f2698c05879afe186ad006bcd2c400d84360c9f550aec365"
  },
  {
   "job_id": "70cdbf0b-0e31-4c03-a74f-5cb2d72dd857",
   "lineage_key": "senior-electric-propulsion-engineer@espoo",
   "title": "Senior Electric Propulsion Engineer",
   "department": "Engineering",
   "team": "Attitude and Orbit Control System Hardware",
   "location": "Espoo",
   "secondary_locations": [
    "Espoo",
    "Warsaw"
   ],
   "employment_type": "FullTime",
   "workplace_type": "Hybrid",
   "is_remote": true,
   "published_at": "2026-06-15T13:53:58.265+00:00",
   "url": "https://jobs.ashbyhq.com/iceye/70cdbf0b-0e31-4c03-a74f-5cb2d72dd857",
   "description_sha256": "8d87bf129f1c7f08457096e2b220c2e4411569de6b04df2afd4425c77a87b9ee"
  },
  {
   "job_id": "72390ec6-b528-445e-b37f-18a61378aaf2",
   "lineage_key": "it-site-engineer-japan@tokyo",
   "title": "IT Site Engineer - Japan",
   "department": "Operations",
   "team": "IT Service & Operations",
   "location": "Tokyo",
   "secondary_locations": [],
   "employment_type": "FullTime",
   "workplace_type": "Hybrid",
   "is_remote": true,
   "published_at": "2026-04-09T09:19:36.211+00:00",
   "url": "https://jobs.ashbyhq.com/iceye/72390ec6-b528-445e-b37f-18a61378aaf2",
   "description_sha256": "2facf6b8d140170c7a5d7e7475ee68ca91401296623e607c6d0d4f910b4292b3"
  },
  {
   "job_id": "728ba3dc-5ab4-4f86-b7cc-5bd24c37f2d4",
   "lineage_key": "optical-ait-engineer@warsaw",
   "title": "Optical AIT Engineer",
   "department": "Global Manufacturing Organization",
   "team": "Production Poland",
   "location": "Warsaw",
   "secondary_locations": [],
   "employment_type": "FullTime",
   "workplace_type": "Hybrid",
   "is_remote": true,
   "published_at": "2026-06-29T17:07:34.404+00:00",
   "url": "https://jobs.ashbyhq.com/iceye/728ba3dc-5ab4-4f86-b7cc-5bd24c37f2d4",
   "description_sha256": "237803fac3cc1d9f94a98af26945cea68f3c0399b503edbd358bc2e1821afb5c"
  },
  {
   "job_id": "7461dbdc-282d-4ba4-afff-8393fc46b277",
   "lineage_key": "engineering-lead-mechanical-engineering@warsaw",
   "title": "Engineering Lead, Mechanical Engineering",
   "department": "Engineering",
   "team": "Optical",
   "location": "Warsaw",
   "secondary_locations": [],
   "employment_type": "FullTime",
   "workplace_type": "Hybrid",
   "is_remote": true,
   "published_at": "2026-04-09T14:22:39.992+00:00",
   "url": "https://jobs.ashbyhq.com/iceye/7461dbdc-282d-4ba4-afff-8393fc46b277",
   "description_sha256": "dd0da1e8dce0eac0a55a784e0980a5e0823dc268485008d109d51346a2ea0cf9"
  },
  {
   "job_id": "75364193-c8d1-4969-9dbb-57d914a40fbb",
   "lineage_key": "spacecraft-analysis-engineer@warsaw",
   "title": "Spacecraft Analysis Engineer",
   "department": "Engineering",
   "team": "Optical System",
   "location": "Warsaw",
   "secondary_locations": [],
   "employment_type": "FullTime",
   "workplace_type": "Hybrid",
   "is_remote": true,
   "published_at": "2026-07-13T19:18:15.803+00:00",
   "url": "https://jobs.ashbyhq.com/iceye/75364193-c8d1-4969-9dbb-57d914a40fbb",
   "description_sha256": "33a86df21af857bb73d1456e2580fa91fae2e670fe6daf1e384f52f09bee19ea"
  },
  {
   "job_id": "76565bc2-919e-4acb-aa0a-96b93d3f4c39",
   "lineage_key": "engineering-operations-manager@espoo",
   "title": "Engineering Operations Manager",
   "department": "Engineering",
   "team": "Engineering Operations Management",
   "location": "Espoo",
   "secondary_locations": [],
   "employment_type": "FullTime",
   "workplace_type": "Hybrid",
   "is_remote": true,
   "published_at": "2026-06-10T08:09:37.953+00:00",
   "url": "https://jobs.ashbyhq.com/iceye/76565bc2-919e-4acb-aa0a-96b93d3f4c39",
   "description_sha256": "e483a81732c0ab3e6aa098ab0dc803facd85e6a03daa4ea334cfd0a44420624d"
  },
  {
   "job_id": "766bfeea-9868-4f0c-a629-5822dce0fa51",
   "lineage_key": "technical-sales-lead@berlin",
   "title": "Technical Sales Lead",
   "department": "Missions",
   "team": "Local Subsidiary, Germany",
   "location": "Berlin",
   "secondary_locations": [],
   "employment_type": "FullTime",
   "workplace_type": "OnSite",
   "is_remote": false,
   "published_at": "2026-06-05T08:34:30.592+00:00",
   "url": "https://jobs.ashbyhq.com/iceye/766bfeea-9868-4f0c-a629-5822dce0fa51",
   "description_sha256": "c692b5517d736e1b56a50b3050eb5cafdfe166cb265fc09229b0af32bfeb22ba"
  },
  {
   "job_id": "769ab01b-1036-4c86-9136-1b522452d8c2",
   "lineage_key": "logistics-specialist-customs-espoo@espoo",
   "title": "Logistics Specialist (Customs) - Espoo",
   "department": "Global Manufacturing Organization",
   "team": "Global Supply Chain",
   "location": "Espoo",
   "secondary_locations": [],
   "employment_type": "FullTime",
   "workplace_type": "Hybrid",
   "is_remote": true,
   "published_at": "2026-06-09T15:13:01.333+00:00",
   "url": "https://jobs.ashbyhq.com/iceye/769ab01b-1036-4c86-9136-1b522452d8c2",
   "description_sha256": "4c4526f88485e50a4102309af69ed7cd86b7e941412b436f56c3e4365214f92e"
  },
  {
   "job_id": "77ee1494-3ca4-4774-a0ad-9e731d63cec1",
   "lineage_key": "senior-electronics-test-engineer@espoo",
   "title": "Senior Electronics Test Engineer",
   "department": "Engineering",
   "team": "Testing Engineering",
   "location": "Espoo",
   "secondary_locations": [],
   "employment_type": "FullTime",
   "workplace_type": "Hybrid",
   "is_remote": true,
   "published_at": "2026-04-08T07:33:55.663+00:00",
   "url": "https://jobs.ashbyhq.com/iceye/77ee1494-3ca4-4774-a0ad-9e731d63cec1",
   "description_sha256": "b6f8d3a45535bd26821c780eff41bf9e5691e6b5f2f8e0d599cd726df555f44a"
  },
  {
   "job_id": "7939fd30-429c-4905-b5f1-cea49915ecfd",
   "lineage_key": "forward-deployed-geospatial-engineer-sar-intelligence-portugal@warsaw",
   "title": "Forward Deployed Geospatial Engineer - SAR Intelligence, Portugal",
   "department": "Forward Deployed Engineering",
   "team": "Forward Deployed Engineering",
   "location": "Warsaw",
   "secondary_locations": [],
   "employment_type": "FullTime",
   "workplace_type": "Hybrid",
   "is_remote": true,
   "published_at": "2026-07-01T08:25:09.894+00:00",
   "url": "https://jobs.ashbyhq.com/iceye/7939fd30-429c-4905-b5f1-cea49915ecfd",
   "description_sha256": "dd62b5c6fb8bad411a6d83d630b98a85c4eaf6f8263149dcd2ef843a6260d8b2"
  },
  {
   "job_id": "7bbb296f-206c-4a56-b757-b9d3099dbc6f",
   "lineage_key": "senior-ai-data-specialist@espoo",
   "title": "Senior AI & Data Specialist",
   "department": "Operations",
   "team": "Operations",
   "location": "Espoo",
   "secondary_locations": [],
   "employment_type": "FullTime",
   "workplace_type": "Hybrid",
   "is_remote": true,
   "published_at": "2026-06-11T08:46:41.061+00:00",
   "url": "https://jobs.ashbyhq.com/iceye/7bbb296f-206c-4a56-b757-b9d3099dbc6f",
   "description_sha256": "0fff45e837fb024d30e61748b54eafb7f278d77ed42c70afea0308487c8213fd"
  },
  {
   "job_id": "7e1be691-32b2-4a35-9338-8fec83b67c55",
   "lineage_key": "electronics-rf-test-team-lead@espoo",
   "title": "Electronics & RF Test Team Lead",
   "department": "Engineering",
   "team": "Testing Engineering",
   "location": "Espoo",
   "secondary_locations": [],
   "employment_type": "FullTime",
   "workplace_type": "Hybrid",
   "is_remote": true,
   "published_at": "2026-06-01T11:19:46.709+00:00",
   "url": "https://jobs.ashbyhq.com/iceye/7e1be691-32b2-4a35-9338-8fec83b67c55",
   "description_sha256": "2fb9b026d275fb7b8ef76df96d038a6b12cf44d2583461b15b15247a4bcc7c76"
  },
  {
   "job_id": "7e9af3f3-e41f-4897-ae9d-e0d536527128",
   "lineage_key": "electronics-test-engineer@espoo",
   "title": "Electronics Test Engineer",
   "department": "Engineering",
   "team": "Testing Engineering",
   "location": "Espoo",
   "secondary_locations": [],
   "employment_type": "FullTime",
   "workplace_type": "Hybrid",
   "is_remote": true,
   "published_at": "2026-07-14T10:49:35.881+00:00",
   "url": "https://jobs.ashbyhq.com/iceye/7e9af3f3-e41f-4897-ae9d-e0d536527128",
   "description_sha256": "218d8862adaef309d9b409ab5628de3cf942eb4e9efbb324a3142205d86d7522"
  },
  {
   "job_id": "8096ddfe-64c4-4555-87ad-45c4e9dc09cd",
   "lineage_key": "supplier-quality-engineer-electronics@espoo",
   "title": "Supplier Quality Engineer (Electronics)",
   "department": "Global Manufacturing Organization",
   "team": "Mission Assurance and Reliability",
   "location": "Espoo",
   "secondary_locations": [],
   "employment_type": "FullTime",
   "workplace_type": "Hybrid",
   "is_remote": true,
   "published_at": "2026-05-13T11:54:23.201+00:00",
   "url": "https://jobs.ashbyhq.com/iceye/8096ddfe-64c4-4555-87ad-45c4e9dc09cd",
   "description_sha256": "b816c8f2a7d28a3eefaefcc3ee319d8c5e2290f9086312566829a5aa68ecaa03"
  },
  {
   "job_id": "83912efc-d73f-4352-8aa7-427d7f53e235",
   "lineage_key": "satellite-production-technician-electronics@valencia",
   "title": "Satellite Production Technician, Electronics",
   "department": "Global Manufacturing Organization",
   "team": "Global Manufacturing Organization",
   "location": "Valencia",
   "secondary_locations": [],
   "employment_type": "FullTime",
   "workplace_type": "OnSite",
   "is_remote": false,
   "published_at": "2026-07-13T11:00:39.495+00:00",
   "url": "https://jobs.ashbyhq.com/iceye/83912efc-d73f-4352-8aa7-427d7f53e235",
   "description_sha256": "0eb2e9f0fcab810cdc71bc28bcc6b30f747065ec9047b25233836898d484ed24"
  },
  {
   "job_id": "8525aea6-9765-41ae-b1c8-87617030564e",
   "lineage_key": "senior-electronics-engineer-avionics@espoo",
   "title": "Senior Electronics Engineer - Avionics",
   "department": "Engineering",
   "team": "Avionics",
   "location": "Espoo",
   "secondary_locations": [],
   "employment_type": "FullTime",
   "workplace_type": "Hybrid",
   "is_remote": true,
   "published_at": "2026-04-08T07:28:21.634+00:00",
   "url": "https://jobs.ashbyhq.com/iceye/8525aea6-9765-41ae-b1c8-87617030564e",
   "description_sha256": "edb49642e39b78391cf48faeed022c9c30362446a0ea5eaf972f40daee5e4ac1"
  },
  {
   "job_id": "855f4bf7-1b9a-4fd9-bff5-d850a487eabb",
   "lineage_key": "office-operations-manager@kyiv",
   "title": "Office & Operations Manager",
   "department": "Operations",
   "team": "Operations",
   "location": "Kyiv ",
   "secondary_locations": [],
   "employment_type": "FullTime",
   "workplace_type": "",
   "is_remote": false,
   "published_at": "2026-07-06T14:58:13.935+00:00",
   "url": "https://jobs.ashbyhq.com/iceye/855f4bf7-1b9a-4fd9-bff5-d850a487eabb",
   "description_sha256": "2839d703514c434aa5b24dbc5197fad3ceaf99366056f706d0ab8d7489d0f6f4"
  },
  {
   "job_id": "879b620d-c9c0-4d71-b642-814fc3996688",
   "lineage_key": "senior-electronics-engineer@warsaw",
   "title": "Senior Electronics Engineer",
   "department": "Engineering",
   "team": "Attitude and Orbit Control System Hardware",
   "location": "Warsaw",
   "secondary_locations": [],
   "employment_type": "FullTime",
   "workplace_type": "OnSite",
   "is_remote": false,
   "published_at": "2026-06-26T12:18:45.905+00:00",
   "url": "https://jobs.ashbyhq.com/iceye/879b620d-c9c0-4d71-b642-814fc3996688",
   "description_sha256": "bdbb0c5a79f3529325eccd95c12c7a6ffef75a8510c15d749968a4eaca9ceb8c"
  },
  {
   "job_id": "8bbb61b2-e417-4d48-b6e2-45843174e21c",
   "lineage_key": "production-reliability-engineer@athens",
   "title": "Production Reliability Engineer",
   "department": "Global Manufacturing Organization",
   "team": "Global Manufacturing Organization",
   "location": "Athens",
   "secondary_locations": [],
   "employment_type": "FullTime",
   "workplace_type": "OnSite",
   "is_remote": false,
   "published_at": "2026-06-12T15:57:20.244+00:00",
   "url": "https://jobs.ashbyhq.com/iceye/8bbb61b2-e417-4d48-b6e2-45843174e21c",
   "description_sha256": "2809ec8a6ffaacd3c0f93886177057401496057a5291498107dc491413586451"
  },
  {
   "job_id": "8c7f1418-b15a-446d-b590-ce24ed00adcf",
   "lineage_key": "head-of-marketing-communications-germany@berlin",
   "title": "Head of Marketing & Communications, Germany",
   "department": "Marketing",
   "team": "Marketing",
   "location": "Berlin",
   "secondary_locations": [],
   "employment_type": "FullTime",
   "workplace_type": "",
   "is_remote": false,
   "published_at": "2026-05-11T08:21:15.547+00:00",
   "url": "https://jobs.ashbyhq.com/iceye/8c7f1418-b15a-446d-b590-ce24ed00adcf",
   "description_sha256": "d8b01f04bb68b83bab6c286c3707ab47d2f5c82e2fe8f6e25d9c1ec0a153a8b1"
  },
  {
   "job_id": "8f1aaed7-9418-49f5-9dcf-c71359b0bc8e",
   "lineage_key": "supply-chain-specialist-mechanics-structures@espoo",
   "title": "Supply Chain Specialist (Mechanics & Structures)",
   "department": "Global Manufacturing Organization",
   "team": "Global Supply Chain",
   "location": "Espoo",
   "secondary_locations": [],
   "employment_type": "FullTime",
   "workplace_type": "Hybrid",
   "is_remote": true,
   "published_at": "2026-04-29T10:59:50.651+00:00",
   "url": "https://jobs.ashbyhq.com/iceye/8f1aaed7-9418-49f5-9dcf-c71359b0bc8e",
   "description_sha256": "08d07b79c53cd95bc6711edea16b95e5a78d2685f6fd42666961b93ecfff66c0"
  },
  {
   "job_id": "8f6aae6f-73d9-4b7e-afb5-9e27089d13d7",
   "lineage_key": "operations-program-manager-maite-finland@espoo",
   "title": "Operations Program Manager, MAITE Finland",
   "department": "Global Manufacturing Organization",
   "team": "Global Manufacturing Organization",
   "location": "Espoo",
   "secondary_locations": [],
   "employment_type": "FullTime",
   "workplace_type": "Hybrid",
   "is_remote": true,
   "published_at": "2026-06-04T15:44:58.947+00:00",
   "url": "https://jobs.ashbyhq.com/iceye/8f6aae6f-73d9-4b7e-afb5-9e27089d13d7",
   "description_sha256": "fa8413cd4151080e3fae5f6a1b83d5150dad0690d41c1ef1c82916238c9fe77d"
  },
  {
   "job_id": "8f7f141e-a48d-409e-96e4-f413afc738f0",
   "lineage_key": "machine-learning-engineer@espoo",
   "title": "Machine Learning Engineer",
   "department": "Solutions",
   "team": "Product Engineering",
   "location": "Espoo",
   "secondary_locations": [],
   "employment_type": "FullTime",
   "workplace_type": "Hybrid",
   "is_remote": true,
   "published_at": "2026-07-02T06:39:30.657+00:00",
   "url": "https://jobs.ashbyhq.com/iceye/8f7f141e-a48d-409e-96e4-f413afc738f0",
   "description_sha256": "42764c9b4bc80cfb8113c9e1a6eb01796e3a2332583cddf2204a816092a09b13"
  },
  {
   "job_id": "9371410f-1664-48c7-8153-466766739c8d",
   "lineage_key": "rf-satellite-systems-software-production-team-lead@valencia",
   "title": "RF, Satellite Systems & Software Production Team Lead",
   "department": "Global Manufacturing Organization",
   "team": "Global Manufacturing Organization",
   "location": "Valencia",
   "secondary_locations": [],
   "employment_type": "FullTime",
   "workplace_type": "OnSite",
   "is_remote": false,
   "published_at": "2026-06-10T17:33:33.984+00:00",
   "url": "https://jobs.ashbyhq.com/iceye/9371410f-1664-48c7-8153-466766739c8d",
   "description_sha256": "4e2142bbefbde8e07e4d9d96b2a68da20f4af0d552ea1c772d3fc8b5c6a28d70"
  },
  {
   "job_id": "945f6b59-8d2b-4bee-92e8-ac3d000d5fa9",
   "lineage_key": "harness-manufacturing-technician@espoo",
   "title": "Harness Manufacturing Technician",
   "department": "Engineering",
   "team": "Spacecraft Hardware",
   "location": "Espoo",
   "secondary_locations": [],
   "employment_type": "FullTime",
   "workplace_type": "OnSite",
   "is_remote": false,
   "published_at": "2026-06-05T07:51:59.020+00:00",
   "url": "https://jobs.ashbyhq.com/iceye/945f6b59-8d2b-4bee-92e8-ac3d000d5fa9",
   "description_sha256": "6f56cb8e94962bad03e6e8d76bdc2cfe695ae33f9f9c2ccc1556db9281e71a0b"
  },
  {
   "job_id": "94b9830e-5093-499c-bbcb-77dac72b5b05",
   "lineage_key": "procurement-manager-athens@greece",
   "title": "Procurement Manager - Athens",
   "department": "Global Manufacturing Organization",
   "team": "Global Supply Chain",
   "location": "Greece",
   "secondary_locations": [],
   "employment_type": "FullTime",
   "workplace_type": "OnSite",
   "is_remote": false,
   "published_at": "2026-06-10T12:16:29.063+00:00",
   "url": "https://jobs.ashbyhq.com/iceye/94b9830e-5093-499c-bbcb-77dac72b5b05",
   "description_sha256": "4d72669975344a8c3da36a8cb6e4d9173510bdd911cb6bedb6b9294717f31a54"
  },
  {
   "job_id": "957356a9-acdf-4504-a1a8-f57c1e98ffcf",
   "lineage_key": "satellite-production-technician-systems-and-software@espoo",
   "title": "Satellite Production Technician, Systems and Software",
   "department": "Global Manufacturing Organization",
   "team": "FI Satellite Production Systems and Software",
   "location": "Espoo",
   "secondary_locations": [],
   "employment_type": "FullTime",
   "workplace_type": "Hybrid",
   "is_remote": true,
   "published_at": "2026-06-04T15:10:16.912+00:00",
   "url": "https://jobs.ashbyhq.com/iceye/957356a9-acdf-4504-a1a8-f57c1e98ffcf",
   "description_sha256": "ff1ef95f4bfe0febe4fef58090c49a2ded8aa0f54900bcde3e9462441d037414"
  },
  {
   "job_id": "9649c999-70dc-4620-9487-e664767fa88d",
   "lineage_key": "satellite-production-senior-technician-rf-systems-software@valencia",
   "title": "Satellite Production Senior Technician, RF, Systems & Software",
   "department": "Global Manufacturing Organization",
   "team": "Global Manufacturing Organization",
   "location": "Valencia",
   "secondary_locations": [],
   "employment_type": "FullTime",
   "workplace_type": "OnSite",
   "is_remote": false,
   "published_at": "2026-07-10T16:00:13.635+00:00",
   "url": "https://jobs.ashbyhq.com/iceye/9649c999-70dc-4620-9487-e664767fa88d",
   "description_sha256": "ccb3dd28af5661625d67b520567acab21668d6d166067439f020f2d9d991d72f"
  },
  {
   "job_id": "96932d24-c2d0-4fe1-b1f6-97221b32ee8e",
   "lineage_key": "release-engineer@espoo",
   "title": "Release Engineer",
   "department": "Engineering",
   "team": "Release Engineering",
   "location": "Espoo",
   "secondary_locations": [],
   "employment_type": "FullTime",
   "workplace_type": "Hybrid",
   "is_remote": true,
   "published_at": "2026-04-08T07:31:58.830+00:00",
   "url": "https://jobs.ashbyhq.com/iceye/96932d24-c2d0-4fe1-b1f6-97221b32ee8e",
   "description_sha256": "b2ce93eca53f0fb5cfb3e64fc3510df341635de77fa50a2e2eb0105fa4c63434"
  },
  {
   "job_id": "96b0096d-df6f-4c0a-acd0-db520a050cee",
   "lineage_key": "forward-deployed-ai-engineer-greece@athens",
   "title": "Forward Deployed AI Engineer, Greece",
   "department": "Forward Deployed Engineering",
   "team": "Forward Deployed Engineering",
   "location": "Athens",
   "secondary_locations": [
    "Athens"
   ],
   "employment_type": "FullTime",
   "workplace_type": "OnSite",
   "is_remote": false,
   "published_at": "2026-06-25T13:50:32.948+00:00",
   "url": "https://jobs.ashbyhq.com/iceye/96b0096d-df6f-4c0a-acd0-db520a050cee",
   "description_sha256": "d12ec77aeb9b975ecd23dc5568a4e5f35e9707471e1906cc67d30577423d9160"
  },
  {
   "job_id": "97431c12-691a-41f4-b7cd-1a6896f43fbd",
   "lineage_key": "operational-excellence-manager@espoo",
   "title": "Operational Excellence Manager",
   "department": "Global Manufacturing Organization",
   "team": "Process Implementation and Standardization",
   "location": "Espoo",
   "secondary_locations": [],
   "employment_type": "FullTime",
   "workplace_type": "OnSite",
   "is_remote": false,
   "published_at": "2026-05-05T06:59:43.638+00:00",
   "url": "https://jobs.ashbyhq.com/iceye/97431c12-691a-41f4-b7cd-1a6896f43fbd",
   "description_sha256": "6eb3928b53dcb777b2f3c3f6d72f49fbd1a38d0bb6bab3bf0bbed0fa1a7d4b1b"
  },
  {
   "job_id": "97cfd417-d59b-41f6-b06a-b6a8defa4054",
   "lineage_key": "pmo-manager@espoo",
   "title": "PMO Manager",
   "department": "Missions",
   "team": "Missions",
   "location": "Espoo",
   "secondary_locations": [],
   "employment_type": "FullTime",
   "workplace_type": "Hybrid",
   "is_remote": true,
   "published_at": "2026-06-26T07:26:56.661+00:00",
   "url": "https://jobs.ashbyhq.com/iceye/97cfd417-d59b-41f6-b06a-b6a8defa4054",
   "description_sha256": "c9860d0bf2ddf9896b5ad2d5686eccead7bb8794bef214849e579d21b5860a10"
  },
  {
   "job_id": "99486007-7a9b-470f-a7ff-e4f886a9c477",
   "lineage_key": "quality-management-system-qms-specialist@greece",
   "title": "Quality Management System (QMS) Specialist",
   "department": "Global Manufacturing Organization",
   "team": "Process Implementation and Standardization",
   "location": "Greece",
   "secondary_locations": [],
   "employment_type": "FullTime",
   "workplace_type": "OnSite",
   "is_remote": false,
   "published_at": "2026-05-25T07:51:21.720+00:00",
   "url": "https://jobs.ashbyhq.com/iceye/99486007-7a9b-470f-a7ff-e4f886a9c477",
   "description_sha256": "512e90805465002f0962918431099e67ecb3112dda559af71e8a00627a7753e9"
  },
  {
   "job_id": "9967722a-e9f3-4b30-9b4c-23bb7586f6c9",
   "lineage_key": "forward-deployed-geospatial-engineer-sar-intelligence-espoo@espoo",
   "title": "Forward Deployed Geospatial Engineer - SAR Intelligence, Espoo",
   "department": "Forward Deployed Engineering",
   "team": "Forward Deployed Engineering",
   "location": "Espoo",
   "secondary_locations": [],
   "employment_type": "FullTime",
   "workplace_type": "Hybrid",
   "is_remote": true,
   "published_at": "2026-07-01T07:40:17.099+00:00",
   "url": "https://jobs.ashbyhq.com/iceye/9967722a-e9f3-4b30-9b4c-23bb7586f6c9",
   "description_sha256": "7d7392a3cf5cc8c6b601b3711376f21d326a22e2cc0b9bc3cd118e698d75cb6d"
  },
  {
   "job_id": "9bff6a57-520b-42bb-a25d-a8fd84833c9f",
   "lineage_key": "physical-security-systems-manager@espoo",
   "title": "Physical Security Systems Manager",
   "department": "IT & Security",
   "team": "IT & Security Staff",
   "location": "Espoo",
   "secondary_locations": [],
   "employment_type": "FullTime",
   "workplace_type": "Hybrid",
   "is_remote": true,
   "published_at": "2026-07-14T08:41:11.033+00:00",
   "url": "https://jobs.ashbyhq.com/iceye/9bff6a57-520b-42bb-a25d-a8fd84833c9f",
   "description_sha256": "40333b61b7c800e6a409d0199af859da40844985ebc3a32899117922b5f53e2e"
  },
  {
   "job_id": "9f3a5bfe-a29a-4c87-9c89-8c0f7d5f77d9",
   "lineage_key": "receptionist-and-management-assistant@valencia-spain",
   "title": "Receptionist and Management Assistant",
   "department": "Missions",
   "team": "Local Subsidiary, Spain",
   "location": "Valencia, Spain",
   "secondary_locations": [],
   "employment_type": "FullTime",
   "workplace_type": "OnSite",
   "is_remote": false,
   "published_at": "2026-07-01T14:49:18.926+00:00",
   "url": "https://jobs.ashbyhq.com/iceye/9f3a5bfe-a29a-4c87-9c89-8c0f7d5f77d9",
   "description_sha256": "24b9dc86424abae1d548946f777a966ab5cbfc35953d036c733ff404d1f469fa"
  },
  {
   "job_id": "a0c0d21d-7086-4579-8e61-3fa52a419804",
   "lineage_key": "power-ait-engineer@valencia",
   "title": "Power AIT Engineer",
   "department": "Global Manufacturing Organization",
   "team": "ES AIT Engineering",
   "location": "Valencia",
   "secondary_locations": [],
   "employment_type": "FullTime",
   "workplace_type": "OnSite",
   "is_remote": false,
   "published_at": "2026-04-09T05:47:53.287+00:00",
   "url": "https://jobs.ashbyhq.com/iceye/a0c0d21d-7086-4579-8e61-3fa52a419804",
   "description_sha256": "ddf11ba33f6cfb6944766f6814abe9eb1164fd82967c316f70a48958054487e1"
  },
  {
   "job_id": "a6db612f-b49f-4be4-a4d4-7639649a1cf7",
   "lineage_key": "head-of-production-maite-finland@espoo",
   "title": "Head of Production, MAITE Finland",
   "department": "Global Manufacturing Organization",
   "team": "Global Manufacturing Organization",
   "location": "Espoo",
   "secondary_locations": [],
   "employment_type": "FullTime",
   "workplace_type": "Hybrid",
   "is_remote": true,
   "published_at": "2026-06-12T15:44:42.371+00:00",
   "url": "https://jobs.ashbyhq.com/iceye/a6db612f-b49f-4be4-a4d4-7639649a1cf7",
   "description_sha256": "ce179b3e7df509f9c69b60e0f4779d874d5e5fde7dd5955e550832190aedff48"
  },
  {
   "job_id": "a878fefb-6160-427a-b74f-8300ec76d77b",
   "lineage_key": "it-engineer@espoo",
   "title": "IT Engineer",
   "department": "Operations",
   "team": "IT",
   "location": "Espoo",
   "secondary_locations": [],
   "employment_type": "FullTime",
   "workplace_type": "Hybrid",
   "is_remote": true,
   "published_at": "2026-05-13T12:00:00.636+00:00",
   "url": "https://jobs.ashbyhq.com/iceye/a878fefb-6160-427a-b74f-8300ec76d77b",
   "description_sha256": "9b9295572ff25a6f9d06eaf14f0781e97bbf78d957fa08686084b5b863a3d57b"
  },
  {
   "job_id": "aabf95c8-9cc7-4de2-95e1-89ff3ca605b9",
   "lineage_key": "software-engineer-unmanned-aircraft-avionics-firmware-autopilot@valencia-spain",
   "title": "Software Engineer, Unmanned Aircraft (Avionics, Firmware, Autopilot)",
   "department": "Engineering",
   "team": "Flight Software",
   "location": "Valencia, Spain",
   "secondary_locations": [],
   "employment_type": "FullTime",
   "workplace_type": "OnSite",
   "is_remote": false,
   "published_at": "2026-05-07T10:08:45.549+00:00",
   "url": "https://jobs.ashbyhq.com/iceye/aabf95c8-9cc7-4de2-95e1-89ff3ca605b9",
   "description_sha256": "b4639d6ae86c9a311057a7a95d4e119869d4d4ab1142a73366917a472dd25677"
  },
  {
   "job_id": "af4bb424-4f4e-451d-b34a-aa86611a61b5",
   "lineage_key": "satellite-electronics-production-team-lead@valencia",
   "title": "Satellite Electronics Production Team Lead",
   "department": "Global Manufacturing Organization",
   "team": "ES AIT Engineering",
   "location": "Valencia",
   "secondary_locations": [],
   "employment_type": "FullTime",
   "workplace_type": "OnSite",
   "is_remote": false,
   "published_at": "2026-06-10T17:28:24.635+00:00",
   "url": "https://jobs.ashbyhq.com/iceye/af4bb424-4f4e-451d-b34a-aa86611a61b5",
   "description_sha256": "02e3e0eaddb1defd8740ca1baf250f8e3b729b316656eb6ebe64bb35af00a139"
  },
  {
   "job_id": "b0ef3dc9-6d59-4388-a64e-1dd6ae77a599",
   "lineage_key": "integration-mechanical-thermal-production-team-lead@valencia",
   "title": "Integration, Mechanical & Thermal Production Team Lead",
   "department": "Global Manufacturing Organization",
   "team": "Global Manufacturing Organization",
   "location": "Valencia",
   "secondary_locations": [],
   "employment_type": "FullTime",
   "workplace_type": "OnSite",
   "is_remote": false,
   "published_at": "2026-06-10T17:24:29.643+00:00",
   "url": "https://jobs.ashbyhq.com/iceye/b0ef3dc9-6d59-4388-a64e-1dd6ae77a599",
   "description_sha256": "38c463571bf0c956e79bde488e47e03d90522bfcf232e236cb964676d684f967"
  },
  {
   "job_id": "b2c9f42a-04af-4cd1-8550-abec4a67e9e1",
   "lineage_key": "quality-control-technician-electronics@athens",
   "title": "Quality Control Technician - Electronics",
   "department": "Global Manufacturing Organization",
   "team": "Production Greece",
   "location": "Athens",
   "secondary_locations": [],
   "employment_type": "FullTime",
   "workplace_type": "OnSite",
   "is_remote": false,
   "published_at": "2026-06-04T15:08:16.365+00:00",
   "url": "https://jobs.ashbyhq.com/iceye/b2c9f42a-04af-4cd1-8550-abec4a67e9e1",
   "description_sha256": "d31a2772fdd5359223ecd23b47b0c1a5e56148bc8c15cd210cba9597e3a1603f"
  },
  {
   "job_id": "b2cdf1d7-086c-4ea6-a76c-388c871a6148",
   "lineage_key": "security-officer-classified-information@berlin",
   "title": "Security Officer - Classified Information",
   "department": "IT & Security",
   "team": "Security",
   "location": "Berlin",
   "secondary_locations": [],
   "employment_type": "FullTime",
   "workplace_type": "OnSite",
   "is_remote": false,
   "published_at": "2026-06-04T15:09:07.832+00:00",
   "url": "https://jobs.ashbyhq.com/iceye/b2cdf1d7-086c-4ea6-a76c-388c871a6148",
   "description_sha256": "db384bb2844ba9819138cdc776c179696512ec15d762863d61bd274a03d55463"
  },
  {
   "job_id": "b8274010-df0f-4321-bd58-2da00918f307",
   "lineage_key": "supply-chain-specialist@valencia",
   "title": "Supply Chain Specialist",
   "department": "Global Manufacturing Organization",
   "team": "Global Supply Chain",
   "location": "Valencia",
   "secondary_locations": [],
   "employment_type": "FullTime",
   "workplace_type": "OnSite",
   "is_remote": false,
   "published_at": "2026-07-13T10:11:05.518+00:00",
   "url": "https://jobs.ashbyhq.com/iceye/b8274010-df0f-4321-bd58-2da00918f307",
   "description_sha256": "dad333a11dcb96db80bdffea0db054dda2670bc3399a642e7baa1298a97cac9c"
  },
  {
   "job_id": "b84b17ba-5619-4909-9f4e-bb1d79e027b5",
   "lineage_key": "mechanical-manufacturing-engineer@espoo",
   "title": "Mechanical Manufacturing Engineer",
   "department": "Engineering",
   "team": "Engineering Manufacturing and QA",
   "location": "Espoo",
   "secondary_locations": [],
   "employment_type": "FullTime",
   "workplace_type": "OnSite",
   "is_remote": false,
   "published_at": "2026-04-14T17:29:07.145+00:00",
   "url": "https://jobs.ashbyhq.com/iceye/b84b17ba-5619-4909-9f4e-bb1d79e027b5",
   "description_sha256": "e71355c57a3cb3c6f9c6f0bd674a803c39bb957f54bb7c67d9356fd41cd831fe"
  },
  {
   "job_id": "b9a28deb-3abb-4a68-9437-6d823cdac199",
   "lineage_key": "embedded-linux-engineer@warsaw",
   "title": "Embedded Linux Engineer",
   "department": "Engineering",
   "team": "Flight Software",
   "location": "Warsaw",
   "secondary_locations": [],
   "employment_type": "FullTime",
   "workplace_type": "Hybrid",
   "is_remote": true,
   "published_at": "2026-07-13T08:51:22.242+00:00",
   "url": "https://jobs.ashbyhq.com/iceye/b9a28deb-3abb-4a68-9437-6d823cdac199",
   "description_sha256": "6c07a7e2676dccc4e68f6aea01e09fcb401287745cbf1764704884546a78b008"
  },
  {
   "job_id": "bb49fc90-0bee-4ee4-8eb8-2771a9a01450",
   "lineage_key": "electronics-engineering-manager-radar-payload-team@espoo",
   "title": "Electronics Engineering Manager, Radar Payload Team",
   "department": "Engineering",
   "team": "Radar Payload",
   "location": "Espoo",
   "secondary_locations": [],
   "employment_type": "FullTime",
   "workplace_type": "Hybrid",
   "is_remote": true,
   "published_at": "2026-04-08T07:29:59.268+00:00",
   "url": "https://jobs.ashbyhq.com/iceye/bb49fc90-0bee-4ee4-8eb8-2771a9a01450",
   "description_sha256": "67e8ceb4af1037d42b9024a38cc750d1f885edc162497545278c3561363c1e86"
  },
  {
   "job_id": "be2a2c66-275f-41b9-acc1-9073b27bfce8",
   "lineage_key": "senior-test-automation-developer@espoo",
   "title": "Senior Test Automation Developer",
   "department": "Engineering",
   "team": "Release Engineering",
   "location": "Espoo",
   "secondary_locations": [],
   "employment_type": "FullTime",
   "workplace_type": "Hybrid",
   "is_remote": true,
   "published_at": "2026-06-12T15:39:07.358+00:00",
   "url": "https://jobs.ashbyhq.com/iceye/be2a2c66-275f-41b9-acc1-9073b27bfce8",
   "description_sha256": "f6a801b48ade9ae6821bd03bbdc423de8f1c39475acfc265a3d18dd54075eac2"
  },
  {
   "job_id": "c02a179c-cf37-4eae-be66-05c3fc49f67d",
   "lineage_key": "forward-deployed-geospatial-engineer-sar-intelligence-poland@lisbon",
   "title": "Forward Deployed Geospatial Engineer - SAR Intelligence, Poland",
   "department": "Forward Deployed Engineering",
   "team": "Forward Deployed Engineering",
   "location": "Lisbon",
   "secondary_locations": [],
   "employment_type": "FullTime",
   "workplace_type": "Hybrid",
   "is_remote": true,
   "published_at": "2026-07-01T08:25:12.815+00:00",
   "url": "https://jobs.ashbyhq.com/iceye/c02a179c-cf37-4eae-be66-05c3fc49f67d",
   "description_sha256": "2576f6ef62b50ed75418cf2975582aacaaf7d89d4f094aadf924591b7d47d9fd"
  },
  {
   "job_id": "c3536786-e2fa-4564-ba73-f26a44a02fde",
   "lineage_key": "satellite-operations-manager@warsaw",
   "title": "Satellite Operations Manager",
   "department": "Engineering",
   "team": "Satellite Operations & Maintenance",
   "location": "Warsaw",
   "secondary_locations": [],
   "employment_type": "FullTime",
   "workplace_type": "Hybrid",
   "is_remote": true,
   "published_at": "2026-04-24T11:34:01.722+00:00",
   "url": "https://jobs.ashbyhq.com/iceye/c3536786-e2fa-4564-ba73-f26a44a02fde",
   "description_sha256": "f09b286b49948a7fa8c929faeb40b8d28f389b8bf382a1ce5c0b2c958dada738"
  },
  {
   "job_id": "c40aa252-a920-4809-8a35-3e7baf59fb11",
   "lineage_key": "customer-excellence-specialist@santiago",
   "title": "Customer Excellence Specialist",
   "department": "Data",
   "team": "Customer Excellence",
   "location": "Santiago",
   "secondary_locations": [
    "Colombia",
    "Brazil",
    "Mexico"
   ],
   "employment_type": "FullTime",
   "workplace_type": "Remote",
   "is_remote": true,
   "published_at": "2026-06-18T15:26:34.304+00:00",
   "url": "https://jobs.ashbyhq.com/iceye/c40aa252-a920-4809-8a35-3e7baf59fb11",
   "description_sha256": "dac61c3b6289b9e1802c79d20e3d1129d6bd729d915e6daa23a59ae8bf777102"
  },
  {
   "job_id": "c51065ca-6ecb-4ce9-9dcb-d48b397dabdd",
   "lineage_key": "electronics-engineer-radar-payload-team@espoo",
   "title": "Electronics Engineer, Radar Payload Team",
   "department": "Engineering",
   "team": "Radar Payload",
   "location": "Espoo",
   "secondary_locations": [],
   "employment_type": "FullTime",
   "workplace_type": "Hybrid",
   "is_remote": true,
   "published_at": "2026-04-08T07:30:17.430+00:00",
   "url": "https://jobs.ashbyhq.com/iceye/c51065ca-6ecb-4ce9-9dcb-d48b397dabdd",
   "description_sha256": "6cc767af7afca8265ef8481a30acfa8b47acd56c91c95faea0be3a6cb0fd87ce"
  },
  {
   "job_id": "c5288409-0aef-4c11-af8f-cbe4e1488926",
   "lineage_key": "forward-deployed-ai-engineer-poland@warsaw",
   "title": "Forward Deployed AI Engineer, Poland",
   "department": "Forward Deployed Engineering",
   "team": "Forward Deployed Engineering",
   "location": "Warsaw",
   "secondary_locations": [],
   "employment_type": "FullTime",
   "workplace_type": "Hybrid",
   "is_remote": true,
   "published_at": "2026-07-02T07:15:10.560+00:00",
   "url": "https://jobs.ashbyhq.com/iceye/c5288409-0aef-4c11-af8f-cbe4e1488926",
   "description_sha256": "d208b0119191d86e52b085024664990b6f6d8b110da216b63e0526a61bf8777d"
  },
  {
   "job_id": "c55cd2d6-021c-4efb-910e-65114b478055",
   "lineage_key": "stock-logistics-manager@warsaw",
   "title": "Stock & Logistics Manager",
   "department": "Global Manufacturing Organization",
   "team": "Global Manufacturing Organization",
   "location": "Warsaw",
   "secondary_locations": [],
   "employment_type": "FullTime",
   "workplace_type": "OnSite",
   "is_remote": false,
   "published_at": "2026-07-03T15:24:56.265+00:00",
   "url": "https://jobs.ashbyhq.com/iceye/c55cd2d6-021c-4efb-910e-65114b478055",
   "description_sha256": "1c41ce53c95a1579db83b0076352969136f18f3be2603176b631d35fd8a8e6b2"
  },
  {
   "job_id": "c5cd00d7-ebd8-4ece-a6e1-be65efb0c783",
   "lineage_key": "stock-and-logistics-manager@valencia",
   "title": "Stock and Logistics Manager",
   "department": "Global Manufacturing Organization",
   "team": "ES Stock Management",
   "location": "Valencia",
   "secondary_locations": [],
   "employment_type": "FullTime",
   "workplace_type": "OnSite",
   "is_remote": false,
   "published_at": "2026-04-09T09:04:17.141+00:00",
   "url": "https://jobs.ashbyhq.com/iceye/c5cd00d7-ebd8-4ece-a6e1-be65efb0c783",
   "description_sha256": "39c01d7bb2171fd1b1963e5b5e77900a4d01ea3c0e406fd20ba171d18a599240"
  },
  {
   "job_id": "c6b51b8b-94af-4007-8464-4a4b858fa5e7",
   "lineage_key": "senior-devops-engineer-core-platform-engineering@espoo",
   "title": "Senior DevOps Engineer - Core Platform Engineering",
   "department": "Engineering",
   "team": "Release Engineering",
   "location": "Espoo",
   "secondary_locations": [],
   "employment_type": "FullTime",
   "workplace_type": "Hybrid",
   "is_remote": true,
   "published_at": "2026-04-22T08:49:14.127+00:00",
   "url": "https://jobs.ashbyhq.com/iceye/c6b51b8b-94af-4007-8464-4a4b858fa5e7",
   "description_sha256": "0f0b9343fa605973016708d3ffe19908e34e06b02c45d65b43ea22b0b2f97ac8"
  },
  {
   "job_id": "c7cf51bc-0164-45cd-a5d9-53f1e4f77845",
   "lineage_key": "engineering-lead-orbit-determination@espoo",
   "title": "Engineering Lead, Orbit Determination",
   "department": "Engineering",
   "team": "Orbit Determination",
   "location": "Espoo",
   "secondary_locations": [],
   "employment_type": "FullTime",
   "workplace_type": "Hybrid",
   "is_remote": true,
   "published_at": "2026-04-14T08:27:19.833+00:00",
   "url": "https://jobs.ashbyhq.com/iceye/c7cf51bc-0164-45cd-a5d9-53f1e4f77845",
   "description_sha256": "fafcc10ce072e84744736739b2f92af54332f748247979a0a24ada9d4804b3f4"
  },
  {
   "job_id": "c9efcbfb-8542-413e-8bbc-4ef9178dab31",
   "lineage_key": "senior-operations-specialist@valencia",
   "title": "Senior Operations Specialist",
   "department": "Engineering",
   "team": "HAPS Avionics and Operations",
   "location": "Valencia",
   "secondary_locations": [],
   "employment_type": "FullTime",
   "workplace_type": "OnSite",
   "is_remote": false,
   "published_at": "2026-05-05T09:05:06.284+00:00",
   "url": "https://jobs.ashbyhq.com/iceye/c9efcbfb-8542-413e-8bbc-4ef9178dab31",
   "description_sha256": "a889a0e4f17d908a01c407aeb0007122a63c963fb21af484fca64ee9ee89c8d3"
  },
  {
   "job_id": "cb38954e-a97b-4340-aa5a-61fd0eeefc55",
   "lineage_key": "satellite-launch-specialist@valencia",
   "title": "Satellite Launch Specialist",
   "department": "Global Manufacturing Organization",
   "team": "Global Manufacturing Organization",
   "location": "Valencia",
   "secondary_locations": [],
   "employment_type": "FullTime",
   "workplace_type": "OnSite",
   "is_remote": false,
   "published_at": "2026-07-13T09:01:44.124+00:00",
   "url": "https://jobs.ashbyhq.com/iceye/cb38954e-a97b-4340-aa5a-61fd0eeefc55",
   "description_sha256": "bce5439c37b5821cc4ff7e15955dacd4eba1c18a770d138d9a37a2a0a96971bb"
  },
  {
   "job_id": "cc0b017f-f910-4e64-9dd6-4b4da5538089",
   "lineage_key": "senior-radio-frequency-engineer@valencia-spain",
   "title": "Senior Radio Frequency Engineer",
   "department": "Engineering",
   "team": "SIGINT",
   "location": "Valencia, Spain",
   "secondary_locations": [],
   "employment_type": "FullTime",
   "workplace_type": "Hybrid",
   "is_remote": true,
   "published_at": "2026-05-27T14:49:35.217+00:00",
   "url": "https://jobs.ashbyhq.com/iceye/cc0b017f-f910-4e64-9dd6-4b4da5538089",
   "description_sha256": "9a394d9849100298e5fbf72f7fef6169a996b7fe626144682955964cae630b1c"
  },
  {
   "job_id": "ce6b9391-c11e-4831-a3f8-39ebd6c23f39",
   "lineage_key": "rf-engineer-radar-payload-team@espoo",
   "title": "RF Engineer, Radar Payload Team",
   "department": "Engineering",
   "team": "Radar Payload",
   "location": "Espoo",
   "secondary_locations": [],
   "employment_type": "FullTime",
   "workplace_type": "Hybrid",
   "is_remote": true,
   "published_at": "2026-04-14T17:30:24.860+00:00",
   "url": "https://jobs.ashbyhq.com/iceye/ce6b9391-c11e-4831-a3f8-39ebd6c23f39",
   "description_sha256": "53d6361fa27a7b27de3f26af751d4bef03e4b6b8e20502eee84650c9cb216aaf"
  },
  {
   "job_id": "cf6ba0e9-a750-4ee7-9b0a-8cb519cb7c39",
   "lineage_key": "staff-platform-engineer-core-platform-engineering@espoo",
   "title": "Staff Platform Engineer - Core Platform Engineering",
   "department": "Engineering",
   "team": "Core Platform Engineering",
   "location": "Espoo",
   "secondary_locations": [],
   "employment_type": "FullTime",
   "workplace_type": "Hybrid",
   "is_remote": true,
   "published_at": "2026-04-08T07:32:56.461+00:00",
   "url": "https://jobs.ashbyhq.com/iceye/cf6ba0e9-a750-4ee7-9b0a-8cb519cb7c39",
   "description_sha256": "3dc94b191a46bda31f13307a092898ccf9790a2e7d7698f197878884fea8e44b"
  },
  {
   "job_id": "cfc19497-d4ed-465d-9b7d-e2ed114c4ba4",
   "lineage_key": "finance-manager-japan@tokyo",
   "title": "Finance Manager - Japan",
   "department": "Finance",
   "team": "Finance",
   "location": "Tokyo",
   "secondary_locations": [],
   "employment_type": "FullTime",
   "workplace_type": "Hybrid",
   "is_remote": true,
   "published_at": "2026-06-30T06:24:45.437+00:00",
   "url": "https://jobs.ashbyhq.com/iceye/cfc19497-d4ed-465d-9b7d-e2ed114c4ba4",
   "description_sha256": "2b2728cff795793897d0611562561ec2159a4964f67671419758c4b3c4d2de5e"
  },
  {
   "job_id": "d00331e7-c38e-4c90-8480-6c0ccbea4a78",
   "lineage_key": "program-manager-netherlands@netherlands",
   "title": "Program Manager - Netherlands",
   "department": "Missions",
   "team": "Missions Programs",
   "location": "Netherlands",
   "secondary_locations": [],
   "employment_type": "FullTime",
   "workplace_type": "Hybrid",
   "is_remote": true,
   "published_at": "2026-06-25T12:27:54.499+00:00",
   "url": "https://jobs.ashbyhq.com/iceye/d00331e7-c38e-4c90-8480-6c0ccbea4a78",
   "description_sha256": "7ad82c43716e27b6b6ec8b377451d69a14c1fc14cf41258468602a3a050e2f27"
  },
  {
   "job_id": "d06fbee7-df97-49e4-90e5-1f9136482c56",
   "lineage_key": "forward-deployed-geospatial-engineer-sar-intelligence-abu-dhabi@united-arab-emirates",
   "title": "Forward Deployed Geospatial Engineer - SAR Intelligence, Abu Dhabi",
   "department": "Forward Deployed Engineering",
   "team": "Forward Deployed Engineering",
   "location": "United Arab Emirates",
   "secondary_locations": [],
   "employment_type": "FullTime",
   "workplace_type": "Hybrid",
   "is_remote": true,
   "published_at": "2026-07-01T07:39:44.482+00:00",
   "url": "https://jobs.ashbyhq.com/iceye/d06fbee7-df97-49e4-90e5-1f9136482c56",
   "description_sha256": "9eb13bdb6750f9bda3e805e3deffa72806d0e863958da86e1f724fcc6085196d"
  },
  {
   "job_id": "d2ea34a4-3f2a-47cb-b107-aefe4628532e",
   "lineage_key": "manufacturing-technician-unmanned-aircraft-fabrication-and-integration@valencia",
   "title": "Manufacturing Technician, Unmanned Aircraft (Fabrication and Integration)",
   "department": "Engineering",
   "team": "HAPS Manufacturing",
   "location": "Valencia",
   "secondary_locations": [],
   "employment_type": "FullTime",
   "workplace_type": "OnSite",
   "is_remote": false,
   "published_at": "2026-04-30T16:28:31.188+00:00",
   "url": "https://jobs.ashbyhq.com/iceye/d2ea34a4-3f2a-47cb-b107-aefe4628532e",
   "description_sha256": "66d65d0e2b911ba0cdc877f98e642e895ff7f14bf7916c59642ec6f5a9ab882f"
  },
  {
   "job_id": "d9a4bdaa-a0bc-4e10-85e2-f99a2ed9b17b",
   "lineage_key": "cnc-and-workshop-assistant@valencia",
   "title": "CNC and Workshop Assistant",
   "department": "Engineering",
   "team": "HAPS",
   "location": "Valencia",
   "secondary_locations": [],
   "employment_type": "FullTime",
   "workplace_type": "OnSite",
   "is_remote": false,
   "published_at": "2026-07-08T15:09:44.591+00:00",
   "url": "https://jobs.ashbyhq.com/iceye/d9a4bdaa-a0bc-4e10-85e2-f99a2ed9b17b",
   "description_sha256": "c0391bf3fc0e36c7ab51e6aed89db4bebc5fa3f516ca948882d3e6662a5190e5"
  },
  {
   "job_id": "d9af7181-4e5c-4ab4-9bca-db371c5c19d6",
   "lineage_key": "system-engineer@espoo",
   "title": "System Engineer",
   "department": "Missions",
   "team": "Missions Product",
   "location": "Espoo",
   "secondary_locations": [
    "Warsaw"
   ],
   "employment_type": "FullTime",
   "workplace_type": "Hybrid",
   "is_remote": true,
   "published_at": "2026-06-10T13:56:16.419+00:00",
   "url": "https://jobs.ashbyhq.com/iceye/d9af7181-4e5c-4ab4-9bca-db371c5c19d6",
   "description_sha256": "bed4f424ce5405083abdc6bf7c03af4baef1691ce63c303cddce57f7dfa750a5"
  },
  {
   "job_id": "dae508db-181a-4d9d-a394-4cc0dbf2950b",
   "lineage_key": "mission-sales-director-nordics@remote",
   "title": "Mission Sales Director, Nordics",
   "department": "Missions",
   "team": "Missions Sales",
   "location": "Remote",
   "secondary_locations": [
    "Stockholm",
    "Espoo",
    "Norway",
    "Denmark"
   ],
   "employment_type": "FullTime",
   "workplace_type": "Remote",
   "is_remote": true,
   "published_at": "2026-06-28T12:54:22.161+00:00",
   "url": "https://jobs.ashbyhq.com/iceye/dae508db-181a-4d9d-a394-4cc0dbf2950b",
   "description_sha256": "74dac61f6b9f3be1f772c44f97b6a45d46ba3c026b8058aab9d32904a85afe3a"
  },
  {
   "job_id": "e03c7457-59ea-49bf-b64b-98e839eb28c8",
   "lineage_key": "devops-engineer@espoo",
   "title": "DevOps Engineer",
   "department": "Missions",
   "team": "Missions",
   "location": "Espoo",
   "secondary_locations": [],
   "employment_type": "FullTime",
   "workplace_type": "Hybrid",
   "is_remote": true,
   "published_at": "2026-06-24T16:03:07.978+00:00",
   "url": "https://jobs.ashbyhq.com/iceye/e03c7457-59ea-49bf-b64b-98e839eb28c8",
   "description_sha256": "d48c51b7b5925131a6abbb320f9a1bec6c9a2199622817c27c905a0535e83042"
  },
  {
   "job_id": "e276cf77-21f8-4509-b926-d9d24fda8d48",
   "lineage_key": "subsystem-assembly-technician@greece",
   "title": "Subsystem Assembly Technician",
   "department": "Global Manufacturing Organization",
   "team": "GR AIT Engineering",
   "location": "Greece",
   "secondary_locations": [],
   "employment_type": "FullTime",
   "workplace_type": "OnSite",
   "is_remote": false,
   "published_at": "2026-04-29T16:43:14.373+00:00",
   "url": "https://jobs.ashbyhq.com/iceye/e276cf77-21f8-4509-b926-d9d24fda8d48",
   "description_sha256": "d69904995d4ccf6e41264d3ee7432b7123cbe818d6bda311c28d8152fa93595d"
  },
  {
   "job_id": "e4d89d32-5bee-4090-8bd0-5634803b6d3f",
   "lineage_key": "satellite-subsystem-test-automation-engineer@espoo",
   "title": "Satellite Subsystem Test Automation Engineer",
   "department": "Global Manufacturing Organization",
   "team": "Digital Transformation & Smart Manufacturing",
   "location": "Espoo",
   "secondary_locations": [],
   "employment_type": "FullTime",
   "workplace_type": "Hybrid",
   "is_remote": true,
   "published_at": "2026-05-29T06:59:32.047+00:00",
   "url": "https://jobs.ashbyhq.com/iceye/e4d89d32-5bee-4090-8bd0-5634803b6d3f",
   "description_sha256": "1bd01fd066c95b8f38f70c84a000ffe025ea1e8f98a65b46f617e917cf54709d"
  },
  {
   "job_id": "ea6fcf8b-f800-4abb-a254-cb82596b5c98",
   "lineage_key": "senior-software-engineer-orbit-control-team@espoo",
   "title": "Senior Software Engineer (Orbit Control team)",
   "department": "Engineering",
   "team": "Orbit Control",
   "location": "Espoo",
   "secondary_locations": [],
   "employment_type": "FullTime",
   "workplace_type": "Hybrid",
   "is_remote": true,
   "published_at": "2026-05-18T10:35:44.037+00:00",
   "url": "https://jobs.ashbyhq.com/iceye/ea6fcf8b-f800-4abb-a254-cb82596b5c98",
   "description_sha256": "a74d390be753c42c3aea98e2e353c1333025a73fdfe502c144bc0a81bd124b5e"
  },
  {
   "job_id": "edf13659-c648-4ca9-9676-cbf002b6aaef",
   "lineage_key": "strategic-account-manager-insurance-and-banking@tokyo",
   "title": "Strategic Account Manager – Insurance and Banking",
   "department": "Solutions",
   "team": "Solutions Sales",
   "location": "Tokyo",
   "secondary_locations": [],
   "employment_type": "FullTime",
   "workplace_type": "Hybrid",
   "is_remote": true,
   "published_at": "2026-04-09T11:48:33.265+00:00",
   "url": "https://jobs.ashbyhq.com/iceye/edf13659-c648-4ca9-9676-cbf002b6aaef",
   "description_sha256": "cd5db3cf1efa40dc4f67ab93317cb841fda6f38f4fcf729ea4bd17887dc46930"
  },
  {
   "job_id": "ef22d62a-7c56-4e49-9d85-c62b045b71d6",
   "lineage_key": "engineering-manager-new-satellite-build-qualification@warsaw",
   "title": "Engineering Manager - New Satellite Build & Qualification",
   "department": "Engineering",
   "team": "Optical",
   "location": "Warsaw",
   "secondary_locations": [],
   "employment_type": "FullTime",
   "workplace_type": "Hybrid",
   "is_remote": true,
   "published_at": "2026-06-08T09:38:56.740+00:00",
   "url": "https://jobs.ashbyhq.com/iceye/ef22d62a-7c56-4e49-9d85-c62b045b71d6",
   "description_sha256": "5b74f090902de89b66750d8c3d498794e2adabd1c2512106cb80b6b34457d502"
  },
  {
   "job_id": "ef4c789d-85da-466c-ac71-0c20cc5a8023",
   "lineage_key": "satellite-production-senior-technician-integration-mechanical-thermal@valencia",
   "title": "Satellite Production Senior Technician, Integration, Mechanical & Thermal",
   "department": "Global Manufacturing Organization",
   "team": "ES Satellite Production",
   "location": "Valencia",
   "secondary_locations": [],
   "employment_type": "FullTime",
   "workplace_type": "OnSite",
   "is_remote": false,
   "published_at": "2026-07-13T10:29:32.734+00:00",
   "url": "https://jobs.ashbyhq.com/iceye/ef4c789d-85da-466c-ac71-0c20cc5a8023",
   "description_sha256": "35f3dd2a616cd794fcf7479a77c78c1fb5a224dac251aa5e275e83fc10602eee"
  },
  {
   "job_id": "f1923306-9ffa-4b2f-bee3-c7472c711167",
   "lineage_key": "forward-deployed-ai-engineer-germany@berlin",
   "title": "Forward Deployed AI Engineer, Germany",
   "department": "Forward Deployed Engineering",
   "team": "Forward Deployed Engineering",
   "location": "Berlin",
   "secondary_locations": [],
   "employment_type": "FullTime",
   "workplace_type": "OnSite",
   "is_remote": false,
   "published_at": "2026-04-22T17:48:57.338+00:00",
   "url": "https://jobs.ashbyhq.com/iceye/f1923306-9ffa-4b2f-bee3-c7472c711167",
   "description_sha256": "bcebb9c1d7c3b0cb1dd0fcfc40e2d87c3aaa0ec3b01b629f7dcb930621edfae8"
  },
  {
   "job_id": "f3a4e7d3-6099-470d-ac0c-e88a9dfc456f",
   "lineage_key": "technical-release-manager@espoo",
   "title": "Technical Release Manager",
   "department": "Engineering",
   "team": "Release Engineering",
   "location": "Espoo",
   "secondary_locations": [],
   "employment_type": "FullTime",
   "workplace_type": "Hybrid",
   "is_remote": true,
   "published_at": "2026-04-08T07:27:00.327+00:00",
   "url": "https://jobs.ashbyhq.com/iceye/f3a4e7d3-6099-470d-ac0c-e88a9dfc456f",
   "description_sha256": "272d3baba596f67805764f1c8eff3885cfb37474d437de14b3953766168b2f89"
  },
  {
   "job_id": "f57cfdfe-3f46-4488-af0e-8465b65efaaf",
   "lineage_key": "electronics-engineer-avionics@espoo",
   "title": "Electronics Engineer - Avionics",
   "department": "Engineering",
   "team": "Avionics",
   "location": "Espoo",
   "secondary_locations": [],
   "employment_type": "FullTime",
   "workplace_type": "Hybrid",
   "is_remote": true,
   "published_at": "2026-04-08T07:27:41.367+00:00",
   "url": "https://jobs.ashbyhq.com/iceye/f57cfdfe-3f46-4488-af0e-8465b65efaaf",
   "description_sha256": "251e2e5ff780e1af7b984a9195bd0f7dfa8034d5ad45451f276081baad334b63"
  },
  {
   "job_id": "f6d34236-1ec0-4567-8b6a-fb6d3eb6bb87",
   "lineage_key": "global-manufacturing-infrastructure-deployment-manager@espoo",
   "title": "Global Manufacturing Infrastructure - Deployment Manager",
   "department": "Global Manufacturing Organization",
   "team": "Global Manufacturing Organization",
   "location": "Espoo",
   "secondary_locations": [],
   "employment_type": "FullTime",
   "workplace_type": "Hybrid",
   "is_remote": true,
   "published_at": "2026-07-01T13:57:44.571+00:00",
   "url": "https://jobs.ashbyhq.com/iceye/f6d34236-1ec0-4567-8b6a-fb6d3eb6bb87",
   "description_sha256": "c3718473e7a46d68c67aa350394aadac4a6e30e14facece3dfe79a28a2223370"
  },
  {
   "job_id": "feed753d-0e9a-4c2e-a7e2-ee3e588e5149",
   "lineage_key": "rf-ait-engineer@valencia",
   "title": "RF AIT Engineer",
   "department": "Global Manufacturing Organization",
   "team": "Global Manufacturing Organization",
   "location": "Valencia",
   "secondary_locations": [],
   "employment_type": "FullTime",
   "workplace_type": "OnSite",
   "is_remote": false,
   "published_at": "2026-07-13T15:31:54.535+00:00",
   "url": "https://jobs.ashbyhq.com/iceye/feed753d-0e9a-4c2e-a7e2-ee3e588e5149",
   "description_sha256": "4dda78618ff9724fa8fafaa7431274754df201859c945ef56104e6bf11b47279"
  }
 ]
}
